{
	"d672109946fe88b803449054": {
		"itemTplToClone": "5ac66cb05acfc40198510a10",
		"parentId": "ASSAULT_RIFLE",
		"handbookParentId": "WEAPONS_ASSAULTRIFLES",
		"overrideProperties": {
			"Prefab": {
				"path": "assets/content/weapons/ak100/weapon_izhmash_ak101_556x45_container.bundle",
				"rcid": ""
			},
			"ConflictingItems":[
				"5a7dbfc1159bd40016548fde"
			],
			"Slots": [
				{
					"_name": "mod_gas_block",
					"_id": "70c1371d3e46c0aa3586cffb",
					"_parent": "d672109946fe88b803449054",
					"_props": {
						"filters": [
							{
								"Shift": 0,
								"Filter": [
									"5a01ad4786f77450561fda02",
									"59c6633186f7740cf0493bb9",
									"59d64ec286f774171d1e0a42",
									"59e649f986f77411d949b246",
									"5b237e425acfc4771e1be0b6",
									"59ccfdba86f7747f2109a587",
									"5cf656f2d7f00c06585fb6eb",
									"5d4aab30a4b9365435358c55",
									"726928d910aacf0b1b40b934",
									"eebec7fdda3d612c25d48af6",
									"4da17d6e133487626488aa2d",
									"f896348f6bab6164ae6e0c2e",
									"4c467c02973c90a5284cb89a"
								]
							}
						]
					},
					"_required": true,
					"_mergeSlotWithChildren": false,
					"_proto": "55d30c4c4bdc2db4468b457e"
				},
				{
					"_name": "mod_launcher",
					"_id": "4c5f003f319114f1ca8933b3",
					"_parent": "d672109946fe88b803449054",
					"_props": {
						"filters": [
							{
								"Shift": 0,
								"Filter": [
									"5648b62b4bdc2d9d488b4585",
									"62e7e7bbe6da9612f743f1e0"
								]
							}
						]
					},
					"_required": false,
					"_mergeSlotWithChildren": false,
					"_proto": "55d30c4c4bdc2db4468b457e"
				},
				{
					"_name": "mod_muzzle",
					"_id": "5622e7d326d0014d360ceb5c",
					"_parent": "d672109946fe88b803449054",
					"_props": {
						"filters": [
							{
								"Shift": 0,
								"Filter": [
									"5ac72e7d5acfc40016339a02",
									"5ac72e895acfc43b321d4bd5",
									"5f633f791b231926f2329f13",
									"5a9ea27ca2750c00137fa672",
									"5cc9ad73d7f00c000e2579d4",
									"5649ab884bdc2ded0b8b457f",
									"59bffc1f86f77435b128b872",
									"5e208b9842457a4a7a33d074",
									"5a0d63621526d8dba31fe3bf",
									"59fb257e86f7742981561852",
									"5a9fbacda2750c00141e080f",
									"65f119212ffe657478130322",
									"46cd26d8aff75c3562a031e5"
								]
							}
						]
					},
					"_required": false,
					"_mergeSlotWithChildren": false,
					"_proto": "55d30c4c4bdc2db4468b457e"
				},
				{
					"_name": "mod_pistol_grip",
					"_id": "b6dd7eaa71b278b7c8b14fe4",
					"_parent": "d672109946fe88b803449054",
					"_props": {
						"filters": [
							{
								"Shift": 0,
								"Filter": [
									"5f6341043ada5942720e2dc5",
									"6087e663132d4d12c81fd96b",
									"5beec8ea0db834001a6f9dbf",
									"5649ad3f4bdc2df8348b4585",
									"5649ade84bdc2d1b2b8b4587",
									"59e62cc886f77440d40b52a1",
									"5a0071d486f77404e23a12b2",
									"57e3dba62459770f0c32322b",
									"5cf54404d7f00c108840b2ef",
									"5e2192a498a36665e8337386",
									"5b30ac585acfc433000eb79c",
									"59e6318286f77444dd62c4cc",
									"5cf50850d7f00c056e24104c",
									"5cf508bfd7f00c056e24104e",
									"5947f92f86f77427344a76b1",
									"5947fa2486f77425b47c1a9b",
									"5c6bf4aa2e2216001219b0ae",
									"5649ae4a4bdc2d1b2b8b4588",
									"5998517986f7746017232f7e",
									"623c3be0484b5003161840dc",
									"628a664bccaab13006640e47",
									"628c9ab845c59e5b80768a81",
									"63f4da90f31d4a33b87bd054",
									"648ae3e356c6310a830fc291",
									"651580dc71a4f10aec4b6056"
								]
							}
						]
					},
					"_required": true,
					"_mergeSlotWithChildren": false,
					"_proto": "55d30c4c4bdc2db4468b457e"
				},
				{
					"_name": "mod_reciever",
					"_id": "ae622de47a2ca64b7738c28a",
					"_parent": "d672109946fe88b803449054",
					"_props": {
						"filters": [
							{
								"Shift": 0,
								"Filter": [
									"5649af094bdc2df8348b4586",
									"5ac50da15acfc4001718d287",
									"5d2c76ed48f03532f2136169",
									"5d2c770c48f0354b4a07c100",
									"5d2c772c48f0355d95672c25",
									"5649af884bdc2d1b2b8b4589",
									"628a665a86cbd9750d2ff5e5"
								]
							}
						]
					},
					"_required": false,
					"_mergeSlotWithChildren": false,
					"_proto": "55d30c4c4bdc2db4468b457e"
				},
				{
					"_name": "mod_sight_rear",
					"_id": "7effc9a1b0d80e8dce1a8e8f",
					"_parent": "d672109946fe88b803449054",
					"_props": {
						"filters": [
							{
								"Shift": 0,
								"Filter": [
									"5ac733a45acfc400192630e2",
									"5649b0544bdc2d1b2b8b458a",
									"5ac72e475acfc400180ae6fe",
									"5649d9a14bdc2d79388b4580",
									"628a7b23b0f75035732dd565",
									"649ec2cec93611967b03495e",
									"5bf3f59f0db834001a6fa060"
								]
							}
						]
					},
					"_required": false,
					"_mergeSlotWithChildren": false,
					"_proto": "55d30c4c4bdc2db4468b457e"
				},
				{
					"_name": "mod_magazine",
					"_id": "ccfe60ef9ce678301a3f4e11",
					"_parent": "d672109946fe88b803449054",
					"_props": {
						"filters": [
							{
								"AnimationIndex": -1,
								"Filter": [
									"5ac66c5d5acfc4001718d314",
									"5c0548ae0db834001966a3c2",
									"c9aeb745fc67045b814af837",
									"4656b02dbe4bfa4a3a9e6d40"
								]
							}
						]
					},
					"_required": false,
					"_mergeSlotWithChildren": false,
					"_proto": "55d30c394bdc2dae468b4577"
				},
				{
					"_name": "mod_stock",
					"_id": "c4a1be6690286aa998fb523f",
					"_parent": "d672109946fe88b803449054",
					"_props": {
						"filters": [
							{
								"Shift": 0,
								"Filter": [
									"5ac50c185acfc400163398d4",
									"5cf50fc5d7f00c056c53f83c",
									"5ac78eaf5acfc4001926317a",
									"5beec8b20db834001961942a",
									"6386300124a1dc425c00577a",
									"649ec87d8007560a9001ab36",
									"185bbb4e20e87b9aec36b1d5",
									"df1d3bfbd9835563f1574809",
									"9d387502b50d1f4b0fb8b0ce"
								]
							}
						]
					}
				},
				{
					"_name": "mod_mount_000",
					"_id": "810b949972c410d3f3b8bfb5",
					"_parent": "d672109946fe88b803449054",
					"_props": {
						"filters": [
							{
								"Shift": 0,
								"Filter": [
									"5947db3f86f77447880cf76f",
									"6113d6c3290d254f5e6b27db",
									"57486e672459770abd687134",
									"618a5d5852ecee1505530b2a",
									"5c82342f2e221644f31c060e",
									"576fd4ec2459777f0b518431",
									"5c82343a2e221644f31c0611",
									"5cf638cbd7f00c06595bc936",
									"5a7c74b3e899ef0014332c29",
									"591ee00d86f774592f7b841e",
									"5d0a29ead7ad1a0026013f27",
									"618a75c9a3884f56c957ca1b",
									"57acb6222459771ec34b5cb0",
									"5c61a40d2e2216001403158d",
									"5c90c3622e221601da359851",
									"638db77630c4240f9e06f8b6",
									"63d114019e35b334d82302f7",
									"6544d4187c5457729210d277"
								]
							}
						]
					},
					"_required": false,
					"_mergeSlotWithChildren": false,
					"_proto": "55d30c4c4bdc2db4468b457e"
				},
				{
					"_name": "mod_charge",
					"_id": "681d7e34f08cec1ffc84136a",
					"_parent": "d672109946fe88b803449054",
					"_props": {
						"filters": [
							{
								"Shift": 0,
								"Filter": [
									"6130ca3fd92c473c77020dbd",
									"5648ac824bdc2ded0b8b457d"
								]
							}
						]
					},
					"_required": false,
					"_mergeSlotWithChildren": false,
					"_proto": "55d30c4c4bdc2db4468b457e"
				}
			],
			"ammoCaliber": "Caliber762x35",
			"defMagType": "5ac66c5d5acfc4001718d314",
			"defAmmo": "5fbe3ffdf8b6a877a729ea82",
			"AdjustCollimatorsToTrajectory": false,
			"shotgunDispersion": 0,
			"Chambers": [
				{
					"_name": "patron_in_weapon",
					"_id": "931589ff68c082b7663e36c2",
					"_parent": "d672109946fe88b803449054",
					"_props": {
						"filters": [
							{
								"Filter": [
									"5fbe3ffdf8b6a877a729ea82",
									"5fd20ff893a8961fc660a954",
									"619636be6db0f2477964e710",
									"6196364158ef8c428c287d9f",
									"6196365d58ef8c428c287da1",
									"64b8725c4b75259c590fa899"
								]
							}
						]
					},
					"_required": false,
					"_mergeSlotWithChildren": false,
					"_proto": "55d4af244bdc2d962f8b4571"
				}
			]
		},
		"locales": {
			"en": {
				"name": "Kalashnikov AK-101 .300 Blackout assault rifle",
				"shortName": "AK-101 .300",
				"description": "A modified version of the Kalashnikov AK-101 that is chambered in .300 blackout."
			}
		},
		"clearClonedProps": false,
		"addtoInventorySlots": [],
		"addtoModSlots": false,
		"modSlot": [],
		"ModdableItemWhitelist": [],
		"ModdableItemBlacklist": [],
		"fleaPriceRoubles": 33800,
		"handbookPriceRoubles": 18397,
		"addtoTraders": true,
		"traderId": "MECHANIC",
		"traderItems": [
			{
				"unlimitedCount": true,
				"stackObjectsCount": 99
			}
		],
		"barterScheme": [
			{
				"count": 42938,
				"_tpl": "ROUBLES"
			}
		],
		"loyallevelitems": 3,
		"addtoBots": false,
		"addtostaticlootcontainer": false,
		"StaticLootContainers": [
			{
				"ContainerName": "LOOTCONTAINER_WEAPON_BOX_4X4",
				"Probability": 250
			},
			{
				"ContainerName": "LOOTCONTAINER_DEAD_SCAV",
				"Probability": 150
			}
		],
		"masteries": true,
		"masterySections": [
			{
				"Name": "AK74",
				"Templates": [
					"d672109946fe88b803449054"
				]
			}
		],
		"addweaponpreset": true,
		"weaponpresets": [
			{
				"_changeWeaponName": false,
				"_encyclopedia": "d672109946fe88b803449054",
				"_id": "660b22d6010010f388362c8a",
				"_items": [
					{
						"_id": "b9cec30083a453fbc6542417",
						"_tpl": "d672109946fe88b803449054",
						"upd": {
							"Repairable": {
								"MaxDurability": 100,
								"Durability": 100
							},
							"Foldable": {
								"Folded": false
							},
							"FireMode": {
								"FireMode": "single"
							}
						}
					},
					{
						"_id": "ca64f44833cae2df78c35e79",
						"_tpl": "59c6633186f7740cf0493bb9",
						"parentId": "b9cec30083a453fbc6542417",
						"slotId": "mod_gas_block"
					},
					{
						"_id": "804b670676b70fc9ad684837",
						"_tpl": "5ac72e7d5acfc40016339a02",
						"parentId": "b9cec30083a453fbc6542417",
						"slotId": "mod_muzzle"
					},
					{
						"_id": "81914b409d64e3d50a1a4763",
						"_tpl": "5649ade84bdc2d1b2b8b4587",
						"parentId": "b9cec30083a453fbc6542417",
						"slotId": "mod_pistol_grip"
					},
					{
						"_id": "fd13d43e734af68ab090ccd3",
						"_tpl": "5ac50da15acfc4001718d287",
						"parentId": "b9cec30083a453fbc6542417",
						"slotId": "mod_reciever"
					},
					{
						"_id": "fcc58ca3419de1ca97ef95ef",
						"_tpl": "5ac72e475acfc400180ae6fe",
						"parentId": "b9cec30083a453fbc6542417",
						"slotId": "mod_sight_rear"
					},
					{
						"_id": "67e959cc23f05f98a967666f",
						"_tpl": "5ac66c5d5acfc4001718d314",
						"parentId": "b9cec30083a453fbc6542417",
						"slotId": "mod_magazine"
					},
					{
						"_id": "87ce24f60c7541a605be917c",
						"_tpl": "5ac50c185acfc400163398d4",
						"parentId": "b9cec30083a453fbc6542417",
						"slotId": "mod_stock"
					},
					{
						"_id": "f3f23dbb11d960a00e53d3ab",
						"_tpl": "5648b1504bdc2d9d488b4584",
						"parentId": "ca64f44833cae2df78c35e79",
						"slotId": "mod_handguard"
					}
				],
				"_name": "AK-101 .300 Stock preset",
				"_parent": "b9cec30083a453fbc6542417",
				"_type": "Preset"
			}
		]
	},
	"939c742f7dad852286188029": {
		"itemTplToClone": "5839a40f24597726f856b511",
		"parentId": "ASSAULT_RIFLE",
		"handbookParentId": "WEAPONS_ASSAULTRIFLES",
		"overrideProperties": {
			"Prefab": {
				"path": "assets/content/weapons/aks74u/weapon_izhmash_aks74ub_545x39_container.bundle",
				"rcid": ""
			},
			"Slots": [
				{
					"_name": "mod_pistol_grip",
					"_id": "be3c51742bd2f6a327ccd04c",
					"_parent": "939c742f7dad852286188029",
					"_props": {
						"filters": [
							{
								"Shift": 0,
								"Filter": [
									"5f6341043ada5942720e2dc5",
									"6087e663132d4d12c81fd96b",
									"5beec8ea0db834001a6f9dbf",
									"5649ad3f4bdc2df8348b4585",
									"5649ade84bdc2d1b2b8b4587",
									"59e62cc886f77440d40b52a1",
									"5a0071d486f77404e23a12b2",
									"57e3dba62459770f0c32322b",
									"5cf54404d7f00c108840b2ef",
									"5e2192a498a36665e8337386",
									"5b30ac585acfc433000eb79c",
									"59e6318286f77444dd62c4cc",
									"5cf50850d7f00c056e24104c",
									"5cf508bfd7f00c056e24104e",
									"5947f92f86f77427344a76b1",
									"5947fa2486f77425b47c1a9b",
									"5c6bf4aa2e2216001219b0ae",
									"5649ae4a4bdc2d1b2b8b4588",
									"5998517986f7746017232f7e",
									"623c3be0484b5003161840dc",
									"628a664bccaab13006640e47",
									"628c9ab845c59e5b80768a81",
									"63f4da90f31d4a33b87bd054",
									"648ae3e356c6310a830fc291",
									"651580dc71a4f10aec4b6056"
								]
							}
						]
					},
					"_required": true,
					"_mergeSlotWithChildren": false,
					"_proto": "55d30c4c4bdc2db4468b457e"
				},
				{
					"_name": "mod_charge",
					"_id": "1b9746298c1ccf5d8b24eb81",
					"_parent": "939c742f7dad852286188029",
					"_props": {
						"filters": [
							{
								"Shift": 0,
								"Filter": [
									"6130ca3fd92c473c77020dbd",
									"5648ac824bdc2ded0b8b457d"
								]
							}
						]
					},
					"_required": false,
					"_mergeSlotWithChildren": false,
					"_proto": "55d30c4c4bdc2db4468b457e"
				},
				{
					"_name": "mod_muzzle",
					"_id": "3ef7f856ba4aab773e2ef50b",
					"_parent": "939c742f7dad852286188029",
					"_props": {
						"filters": [
							{
								"Shift": 0,
								"Filter": [
									"5ac72e7d5acfc40016339a02",
									"5ac72e895acfc43b321d4bd5",
									"5f633f791b231926f2329f13",
									"5a9ea27ca2750c00137fa672",
									"5cc9ad73d7f00c000e2579d4",
									"5649ab884bdc2ded0b8b457f",
									"59bffc1f86f77435b128b872",
									"5e208b9842457a4a7a33d074",
									"5a0d63621526d8dba31fe3bf",
									"59fb257e86f7742981561852",
									"5a9fbacda2750c00141e080f",
									"65f119212ffe657478130322",
									"46cd26d8aff75c3562a031e5"
								]
							}
						]
					},
					"_required": false,
					"_mergeSlotWithChildren": false,
					"_proto": "55d30c4c4bdc2db4468b457e"
				},
				{
					"_name": "mod_magazine",
					"_id": "b303e7c69c8ab92d33068993",
					"_parent": "939c742f7dad852286188029",
					"_props": {
						"filters": [
							{
								"AnimationIndex": -1,
								"Filter": [
									"5ac66c5d5acfc4001718d314",
									"5c0548ae0db834001966a3c2",
									"c9aeb745fc67045b814af837",
									"4656b02dbe4bfa4a3a9e6d40"
								]
							}
						]
					},
					"_required": false,
					"_mergeSlotWithChildren": false,
					"_proto": "55d30c394bdc2dae468b4577"
				},
				{
					"_name": "mod_stock",
					"_id": "cf43ef162c5f15fa2473a6b4",
					"_parent": "939c742f7dad852286188029",
					"_props": {
						"filters": [
							{
								"Shift": 0,
								"Filter": [
									"59ecc28286f7746d7a68aa8c",
									"5ab626e4d8ce87272e4c6e43",
									"57dc347d245977596754e7a1",
									"185bbb4e20e87b9aec36b1d5",
									"df1d3bfbd9835563f1574809",
									"9d387502b50d1f4b0fb8b0ce"
								]
							}
						]
					}
				},
				{
					"_name": "mod_reciever",
					"_id": "d1929bed11ae9d891f8fd1b5",
					"_parent": "939c742f7dad852286188029",
					"_props": {
						"filters": [
							{
								"Shift": 0,
								"Filter": [
									"57dc334d245977597164366f",
									"5839a7742459773cf9693481",
									"655cb6b5d680a544f30607fa"
								]
							}
						]
					},
					"_required": false,
					"_mergeSlotWithChildren": false,
					"_proto": "55d30c4c4bdc2db4468b457e"
				},
				{
					"_name": "mod_mount_000",
					"_id": "e8b83ec99efa511b8b61dedc",
					"_parent": "939c742f7dad852286188029",
					"_props": {
						"filters": [
							{
								"Shift": 0,
								"Filter": [
									"5947db3f86f77447880cf76f",
									"6113d6c3290d254f5e6b27db",
									"57486e672459770abd687134",
									"618a5d5852ecee1505530b2a",
									"5c82342f2e221644f31c060e",
									"576fd4ec2459777f0b518431",
									"5c82343a2e221644f31c0611",
									"5cf638cbd7f00c06595bc936",
									"5a7c74b3e899ef0014332c29",
									"591ee00d86f774592f7b841e",
									"5d0a29ead7ad1a0026013f27",
									"618a75c9a3884f56c957ca1b",
									"57acb6222459771ec34b5cb0",
									"5c61a40d2e2216001403158d",
									"5c90c3622e221601da359851",
									"638db77630c4240f9e06f8b6",
									"63d114019e35b334d82302f7",
									"6544d4187c5457729210d277"
								]
							}
						]
					},
					"_required": false,
					"_mergeSlotWithChildren": false,
					"_proto": "55d30c4c4bdc2db4468b457e"
				},
				{
					"_name": "mod_gas_block",
					"_id": "15eb020b1f8765da42633073",
					"_parent": "939c742f7dad852286188029",
					"_props": {
						"filters": [
							{
								"Shift": 0,
								"Filter": [
									"59d36a0086f7747e673f3946"
								]
							}
						]
					},
					"_required": true,
					"_mergeSlotWithChildren": false,
					"_proto": "55d30c4c4bdc2db4468b457e"
				}
			],
			"ammoCaliber": "Caliber762x35",
			"defMagType": "5ac66c5d5acfc4001718d314",
			"defAmmo": "5fbe3ffdf8b6a877a729ea82",
			"AdjustCollimatorsToTrajectory": false,
			"shotgunDispersion": 0,
			"Chambers": [
				{
					"_name": "patron_in_weapon",
					"_id": "9da1c3bad88d8ff63b776437",
					"_parent": "939c742f7dad852286188029",
					"_props": {
						"filters": [
							{
								"Filter": [
									"5fbe3ffdf8b6a877a729ea82",
									"5fd20ff893a8961fc660a954",
									"619636be6db0f2477964e710",
									"6196364158ef8c428c287d9f",
									"6196365d58ef8c428c287da1",
									"64b8725c4b75259c590fa899"
								]
							}
						]
					},
					"_required": false,
					"_mergeSlotWithChildren": false,
					"_proto": "55d4af244bdc2d962f8b4571"
				}
			]
		},
		"locales": {
			"en": {
				"name": "Kalashnikov AKS-74UB .300 Blackout Assault Rifle",
				"shortName": "AKS-74UB .300",
				"description": "A modified version of the Kalashnikov AKS-74UB that is chambered in .300 blackout."
			}
		},
		"clearClonedProps": false,
		"addtoInventorySlots": [],
		"addtoModSlots": false,
		"modSlot": [],
		"ModdableItemWhitelist": [],
		"ModdableItemBlacklist": [],
		"fleaPriceRoubles": 81248,
		"handbookPriceRoubles": 21746,
		"addtoTraders": true,
		"traderId": "PRAPOR",
		"traderItems": [
			{
				"unlimitedCount": true,
				"stackObjectsCount": 99
			}
		],
		"barterScheme": [
			{
				"count": 26260,
				"_tpl": "ROUBLES"
			}
		],
		"loyallevelitems": 2,
		"addtoBots": false,
		"addtostaticlootcontainer": false,
		"StaticLootContainers": [
			{
				"ContainerName": "LOOTCONTAINER_WEAPON_BOX_4X4",
				"Probability": 250
			},
			{
				"ContainerName": "LOOTCONTAINER_DEAD_SCAV",
				"Probability": 150
			}
		],
		"masteries": true,
		"masterySections": [
			{
				"Name": "AKSU",
				"Templates": [
					"939c742f7dad852286188029"
				]
			}
		],
		"addweaponpreset": true,
		"weaponpresets": [
			{
				"_changeWeaponName": false,
				"_encyclopedia": "939c742f7dad852286188029",
				"_id": "660b23e9010010f3880b2001",
				"_items": [
					{
						"_id": "3e4e40e95d668a5ac8afdd51",
						"_tpl": "939c742f7dad852286188029",
						"upd": {
							"Repairable": {
								"MaxDurability": 100,
								"Durability": 100
							},
							"Foldable": {
								"Folded": false
							},
							"FireMode": {
								"FireMode": "single"
							}
						}
					},
					{
						"_id": "a3ef4d4387cf8dca427e2e3b",
						"_tpl": "57e3dba62459770f0c32322b",
						"parentId": "3e4e40e95d668a5ac8afdd51",
						"slotId": "mod_pistol_grip"
					},
					{
						"_id": "c0cfc9efb127c33c32ccb968",
						"_tpl": "5a0d63621526d8dba31fe3bf",
						"parentId": "3e4e40e95d668a5ac8afdd51",
						"slotId": "mod_muzzle"
					},
					{
						"_id": "a839b60c3d16cc6c20c4ecad",
						"_tpl": "5ac66c5d5acfc4001718d314",
						"parentId": "3e4e40e95d668a5ac8afdd51",
						"slotId": "mod_magazine"
					},
					{
						"_id": "e1d50aa71fe08311cdc55790",
						"_tpl": "57dc347d245977596754e7a1",
						"parentId": "3e4e40e95d668a5ac8afdd51",
						"slotId": "mod_stock"
					},
					{
						"_id": "3c0a7514fb62ec631ce78db1",
						"_tpl": "5839a7742459773cf9693481",
						"parentId": "3e4e40e95d668a5ac8afdd51",
						"slotId": "mod_reciever"
					},
					{
						"_id": "7a8a2e26ff237b06a1298841",
						"_tpl": "59d36a0086f7747e673f3946",
						"parentId": "3e4e40e95d668a5ac8afdd51",
						"slotId": "mod_gas_block"
					},
					{
						"_id": "595a52c769891e24bd080bf8",
						"_tpl": "57dc32dc245977596d4ef3d3",
						"parentId": "7a8a2e26ff237b06a1298841",
						"slotId": "mod_handguard"
					}
				],
				"_name": "AKS-74UB .300 Stock preset",
				"_parent": "3e4e40e95d668a5ac8afdd51",
				"_type": "Preset"
			}
		]
	},
	"627c4fe34b0a558e8a3642a1": {
		"itemTplToClone": "583990e32459771419544dd2",
		"parentId": "ASSAULT_RIFLE",
		"handbookParentId": "WEAPONS_ASSAULTRIFLES",
		"overrideProperties": {
			"Prefab": {
				"path": "assets/content/weapons/aks74u/weapon_izhmash_aks74ub_545x39_container.bundle",
				"rcid": ""
			},
			"Slots": [
				{
					"_name": "mod_pistol_grip",
					"_id": "c93154523f4a6c3625f50c13",
					"_parent": "627c4fe34b0a558e8a3642a1",
					"_props": {
						"filters": [
							{
								"Shift": 0,
								"Filter": [
									"5f6341043ada5942720e2dc5",
									"6087e663132d4d12c81fd96b",
									"5beec8ea0db834001a6f9dbf",
									"5649ad3f4bdc2df8348b4585",
									"5649ade84bdc2d1b2b8b4587",
									"59e62cc886f77440d40b52a1",
									"5a0071d486f77404e23a12b2",
									"57e3dba62459770f0c32322b",
									"5cf54404d7f00c108840b2ef",
									"5e2192a498a36665e8337386",
									"5b30ac585acfc433000eb79c",
									"59e6318286f77444dd62c4cc",
									"5cf50850d7f00c056e24104c",
									"5cf508bfd7f00c056e24104e",
									"5947f92f86f77427344a76b1",
									"5947fa2486f77425b47c1a9b",
									"5c6bf4aa2e2216001219b0ae",
									"5649ae4a4bdc2d1b2b8b4588",
									"5998517986f7746017232f7e",
									"623c3be0484b5003161840dc",
									"628a664bccaab13006640e47",
									"628c9ab845c59e5b80768a81",
									"63f4da90f31d4a33b87bd054",
									"648ae3e356c6310a830fc291",
									"651580dc71a4f10aec4b6056"
								]
							}
						]
					},
					"_required": true,
					"_mergeSlotWithChildren": false,
					"_proto": "55d30c4c4bdc2db4468b457e"
				},
				{
					"_name": "mod_charge",
					"_id": "322cdeecde66d77195ad5b24",
					"_parent": "627c4fe34b0a558e8a3642a1",
					"_props": {
						"filters": [
							{
								"Shift": 0,
								"Filter": [
									"6130ca3fd92c473c77020dbd",
									"5648ac824bdc2ded0b8b457d"
								]
							}
						]
					},
					"_required": false,
					"_mergeSlotWithChildren": false,
					"_proto": "55d30c4c4bdc2db4468b457e"
				},
				{
					"_name": "mod_muzzle",
					"_id": "958dd79c083302545876024c",
					"_parent": "627c4fe34b0a558e8a3642a1",
					"_props": {
						"filters": [
							{
								"Shift": 0,
								"Filter": [
									"5ac72e7d5acfc40016339a02",
									"5ac72e895acfc43b321d4bd5",
									"5f633f791b231926f2329f13",
									"5a9ea27ca2750c00137fa672",
									"5cc9ad73d7f00c000e2579d4",
									"5649ab884bdc2ded0b8b457f",
									"59bffc1f86f77435b128b872",
									"5e208b9842457a4a7a33d074",
									"5a0d63621526d8dba31fe3bf",
									"59fb257e86f7742981561852",
									"5a9fbacda2750c00141e080f",
									"65f119212ffe657478130322",
									"46cd26d8aff75c3562a031e5"
								]
							}
						]
					},
					"_required": false,
					"_mergeSlotWithChildren": false,
					"_proto": "55d30c4c4bdc2db4468b457e"
				},
				{
					"_name": "mod_magazine",
					"_id": "8302721828378612e6b7606b",
					"_parent": "627c4fe34b0a558e8a3642a1",
					"_props": {
						"filters": [
							{
								"AnimationIndex": -1,
								"Filter": [
									"5ac66c5d5acfc4001718d314",
									"5c0548ae0db834001966a3c2",
									"c9aeb745fc67045b814af837",
									"4656b02dbe4bfa4a3a9e6d40"
								]
							}
						]
					},
					"_required": false,
					"_mergeSlotWithChildren": false,
					"_proto": "55d30c394bdc2dae468b4577"
				},
				{
					"_name": "mod_stock",
					"_id": "e491e997689f6de10bb99dd0",
					"_parent": "627c4fe34b0a558e8a3642a1",
					"_props": {
						"filters": [
							{
								"Shift": 0,
								"Filter": [
									"59ecc28286f7746d7a68aa8c",
									"5ab626e4d8ce87272e4c6e43",
									"57dc347d245977596754e7a1",
									"185bbb4e20e87b9aec36b1d5",
									"df1d3bfbd9835563f1574809",
									"9d387502b50d1f4b0fb8b0ce"
								]
							}
						]
					}
				},
				{
					"_name": "mod_reciever",
					"_id": "d7e7db7cf019f1cb29d9bed7",
					"_parent": "627c4fe34b0a558e8a3642a1",
					"_props": {
						"filters": [
							{
								"Shift": 0,
								"Filter": [
									"57dc334d245977597164366f",
									"5839a7742459773cf9693481",
									"655cb6b5d680a544f30607fa"
								]
							}
						]
					},
					"_required": false,
					"_mergeSlotWithChildren": false,
					"_proto": "55d30c4c4bdc2db4468b457e"
				},
				{
					"_name": "mod_mount_000",
					"_id": "a1a6d77cc4af5683b85a3e96",
					"_parent": "627c4fe34b0a558e8a3642a1",
					"_props": {
						"filters": [
							{
								"Shift": 0,
								"Filter": [
									"5947db3f86f77447880cf76f",
									"6113d6c3290d254f5e6b27db",
									"57486e672459770abd687134",
									"618a5d5852ecee1505530b2a",
									"5c82342f2e221644f31c060e",
									"576fd4ec2459777f0b518431",
									"5c82343a2e221644f31c0611",
									"5cf638cbd7f00c06595bc936",
									"5a7c74b3e899ef0014332c29",
									"591ee00d86f774592f7b841e",
									"5d0a29ead7ad1a0026013f27",
									"618a75c9a3884f56c957ca1b",
									"57acb6222459771ec34b5cb0",
									"5c61a40d2e2216001403158d",
									"5c90c3622e221601da359851",
									"638db77630c4240f9e06f8b6",
									"63d114019e35b334d82302f7",
									"6544d4187c5457729210d277"
								]
							}
						]
					},
					"_required": false,
					"_mergeSlotWithChildren": false,
					"_proto": "55d30c4c4bdc2db4468b457e"
				},
				{
					"_name": "mod_gas_block",
					"_id": "b1d5e3ab983d9a977514d3b8",
					"_parent": "627c4fe34b0a558e8a3642a1",
					"_props": {
						"filters": [
							{
								"Shift": 0,
								"Filter": [
									"59d36a0086f7747e673f3946"
								]
							}
						]
					},
					"_required": true,
					"_mergeSlotWithChildren": false,
					"_proto": "55d30c4c4bdc2db4468b457e"
				}
			],
			"ammoCaliber": "Caliber762x35",
			"defMagType": "5ac66c5d5acfc4001718d314",
			"defAmmo": "5fbe3ffdf8b6a877a729ea82",
			"AdjustCollimatorsToTrajectory": false,
			"shotgunDispersion": 0,
			"Chambers": [
				{
					"_name": "patron_in_weapon",
					"_id": "fa96f39be80152b330a7455a",
					"_parent": "627c4fe34b0a558e8a3642a1",
					"_props": {
						"filters": [
							{
								"Filter": [
									"5fbe3ffdf8b6a877a729ea82",
									"5fd20ff893a8961fc660a954",
									"619636be6db0f2477964e710",
									"6196364158ef8c428c287d9f",
									"6196365d58ef8c428c287da1",
									"64b8725c4b75259c590fa899"
								]
							}
						]
					},
					"_required": false,
					"_mergeSlotWithChildren": false,
					"_proto": "55d4af244bdc2d962f8b4571"
				}
			]
		},
		"locales": {
			"en": {
				"name": "Kalashnikov AKS-74UN .300 Blackout Assault Rifle",
				"shortName": "AKS-74UN .300",
				"description": "A modified version of the Kalashnikov AKS-74UN that is chambered in .300 blackout."
			}
		},
		"clearClonedProps": false,
		"addtoInventorySlots": [],
		"addtoModSlots": false,
		"modSlot": [],
		"ModdableItemWhitelist": [],
		"ModdableItemBlacklist": [],
		"fleaPriceRoubles": 32800,
		"handbookPriceRoubles": 19345,
		"addtoTraders": true,
		"traderId": "PRAPOR",
		"traderItems": [
			{
				"unlimitedCount": true,
				"stackObjectsCount": 99
			}
		],
		"barterScheme": [
			{
				"count": 22025,
				"_tpl": "ROUBLES"
			}
		],
		"loyallevelitems": 2,
		"addtoBots": false,
		"addtostaticlootcontainer": false,
		"StaticLootContainers": [
			{
				"ContainerName": "LOOTCONTAINER_WEAPON_BOX_4X4",
				"Probability": 250
			},
			{
				"ContainerName": "LOOTCONTAINER_DEAD_SCAV",
				"Probability": 150
			}
		],
		"masteries": true,
		"masterySections": [
			{
				"Name": "AKSU",
				"Templates": [
					"627c4fe34b0a558e8a3642a1"
				]
			}
		],
		"addweaponpreset": true,
		"weaponpresets": [
			{
				"_changeWeaponName": false,
				"_encyclopedia": "627c4fe34b0a558e8a3642a1",
				"_id": "660b2422010010f3881eaee3",
				"_items": [
					{
						"_id": "d4b0aab0f7484102cf001907",
						"_tpl": "627c4fe34b0a558e8a3642a1",
						"upd": {
							"Repairable": {
								"MaxDurability": 100,
								"Durability": 100
							},
							"Foldable": {
								"Folded": false
							},
							"FireMode": {
								"FireMode": "single"
							}
						}
					},
					{
						"_id": "c13c9cfba723e097222154b6",
						"_tpl": "57e3dba62459770f0c32322b",
						"parentId": "d4b0aab0f7484102cf001907",
						"slotId": "mod_pistol_grip"
					},
					{
						"_id": "972eaabd80aaf379c64b5570",
						"_tpl": "5ac72e895acfc43b321d4bd5",
						"parentId": "d4b0aab0f7484102cf001907",
						"slotId": "mod_muzzle"
					},
					{
						"_id": "15e16e1e1ac92adb9fd97cbc",
						"_tpl": "5ac66c5d5acfc4001718d314",
						"parentId": "d4b0aab0f7484102cf001907",
						"slotId": "mod_magazine"
					},
					{
						"_id": "9b9743fb8fef8b3268e3edcf",
						"_tpl": "57dc347d245977596754e7a1",
						"parentId": "d4b0aab0f7484102cf001907",
						"slotId": "mod_stock"
					},
					{
						"_id": "dc3c0a163ee23c4f471db633",
						"_tpl": "57dc334d245977597164366f",
						"parentId": "d4b0aab0f7484102cf001907",
						"slotId": "mod_reciever"
					},
					{
						"_id": "255a3e121fa741f126fc6a2a",
						"_tpl": "59d36a0086f7747e673f3946",
						"parentId": "d4b0aab0f7484102cf001907",
						"slotId": "mod_gas_block"
					},
					{
						"_id": "caa3925c6cf8d00019e983cd",
						"_tpl": "57dc32dc245977596d4ef3d3",
						"parentId": "255a3e121fa741f126fc6a2a",
						"slotId": "mod_handguard"
					}
				],
				"_name": "AKS-74UN .300 Stock preset",
				"_parent": "d4b0aab0f7484102cf001907",
				"_type": "Preset"
			}
		]
	},
	"ed05294ed53c0400ae0e8a55": {
		"itemTplToClone": "57dc2fa62459775949412633",
		"parentId": "ASSAULT_RIFLE",
		"handbookParentId": "WEAPONS_ASSAULTRIFLES",
		"overrideProperties": {
			"Prefab": {
				"path": "assets/content/weapons/aks74u/weapon_izhmash_aks74u_545x39_container.bundle",
				"rcid": ""
			},
			"Slots": [
				{
					"_name": "mod_pistol_grip",
					"_id": "78715477591ab52f74c524af",
					"_parent": "ed05294ed53c0400ae0e8a55",
					"_props": {
						"filters": [
							{
								"Shift": 0,
								"Filter": [
									"5f6341043ada5942720e2dc5",
									"6087e663132d4d12c81fd96b",
									"5beec8ea0db834001a6f9dbf",
									"5649ad3f4bdc2df8348b4585",
									"5649ade84bdc2d1b2b8b4587",
									"59e62cc886f77440d40b52a1",
									"5a0071d486f77404e23a12b2",
									"57e3dba62459770f0c32322b",
									"5cf54404d7f00c108840b2ef",
									"5e2192a498a36665e8337386",
									"5b30ac585acfc433000eb79c",
									"59e6318286f77444dd62c4cc",
									"5cf50850d7f00c056e24104c",
									"5cf508bfd7f00c056e24104e",
									"5947f92f86f77427344a76b1",
									"5947fa2486f77425b47c1a9b",
									"5c6bf4aa2e2216001219b0ae",
									"5649ae4a4bdc2d1b2b8b4588",
									"5998517986f7746017232f7e",
									"623c3be0484b5003161840dc",
									"628c9ab845c59e5b80768a81",
									"628a664bccaab13006640e47",
									"63f4da90f31d4a33b87bd054",
									"648ae3e356c6310a830fc291",
									"651580dc71a4f10aec4b6056"
								]
							}
						]
					},
					"_required": true,
					"_mergeSlotWithChildren": false,
					"_proto": "55d30c4c4bdc2db4468b457e"
				},
				{
					"_name": "mod_muzzle",
					"_id": "78715477591ab52f74c524af",
					"_parent": "ed05294ed53c0400ae0e8a55",
					"_props": {
						"filters": [
							{
								"Shift": 0,
								"Filter": [
									"5ac72e7d5acfc40016339a02",
									"5ac72e895acfc43b321d4bd5",
									"5f633f791b231926f2329f13",
									"5a9ea27ca2750c00137fa672",
									"5cc9ad73d7f00c000e2579d4",
									"5649ab884bdc2ded0b8b457f",
									"59bffc1f86f77435b128b872",
									"5e208b9842457a4a7a33d074",
									"5a0d63621526d8dba31fe3bf",
									"59fb257e86f7742981561852",
									"5a9fbacda2750c00141e080f",
									"65f119212ffe657478130322",
									"46cd26d8aff75c3562a031e5"
								]
							}
						]
					},
					"_required": false,
					"_mergeSlotWithChildren": false,
					"_proto": "55d30c4c4bdc2db4468b457e"
				},
				{
					"_name": "mod_charge",
					"_id": "b2354827bbdee138245e2a69",
					"_parent": "ed05294ed53c0400ae0e8a55",
					"_props": {
						"filters": [
							{
								"Shift": 0,
								"Filter": [
									"6130ca3fd92c473c77020dbd",
									"5648ac824bdc2ded0b8b457d"
								]
							}
						]
					},
					"_required": false,
					"_mergeSlotWithChildren": false,
					"_proto": "55d30c4c4bdc2db4468b457e"
				},
				{
					"_name": "mod_magazine",
					"_id": "da5c9e87bf2337c93ecf4ee9",
					"_parent": "ed05294ed53c0400ae0e8a55",
					"_props": {
						"filters": [
							{
								"AnimationIndex": -1,
								"Filter": [
									"5ac66c5d5acfc4001718d314",
									"5c0548ae0db834001966a3c2",
									"c9aeb745fc67045b814af837",
									"4656b02dbe4bfa4a3a9e6d40"
								]
							}
						]
					},
					"_required": false,
					"_mergeSlotWithChildren": false,
					"_proto": "55d30c394bdc2dae468b4577"
				},
				{
					"_name": "mod_stock",
					"_id": "41ea96559bee5acc848ef00d",
					"_parent": "ed05294ed53c0400ae0e8a55",
					"_props": {
						"filters": [
							{
								"Shift": 0,
								"Filter": [
									"59ecc28286f7746d7a68aa8c",
									"5ab626e4d8ce87272e4c6e43",
									"57dc347d245977596754e7a1",
									"185bbb4e20e87b9aec36b1d5",
									"df1d3bfbd9835563f1574809",
									"9d387502b50d1f4b0fb8b0ce"
								]
							}
						]
					}
				},
				{
					"_name": "mod_reciever",
					"_id": "6226b30bfb0e51d298fd9e52",
					"_parent": "ed05294ed53c0400ae0e8a55",
					"_props": {
						"filters": [
							{
								"Shift": 0,
								"Filter": [
									"57dc334d245977597164366f",
									"5839a7742459773cf9693481",
									"655cb6b5d680a544f30607fa"
								]
							}
						]
					},
					"_required": false,
					"_mergeSlotWithChildren": false,
					"_proto": "55d30c4c4bdc2db4468b457e"
				},
				{
					"_name": "mod_gas_block",
					"_id": "51f47ef9f884cb709697579b",
					"_parent": "ed05294ed53c0400ae0e8a55",
					"_props": {
						"filters": [
							{
								"Shift": 0,
								"Filter": [
									"59d36a0086f7747e673f3946"
								]
							}
						]
					},
					"_required": true,
					"_mergeSlotWithChildren": false,
					"_proto": "55d30c4c4bdc2db4468b457e"
				}
			],
			"ammoCaliber": "Caliber762x35",
			"defMagType": "5ac66c5d5acfc4001718d314",
			"defAmmo": "5fbe3ffdf8b6a877a729ea82",
			"AdjustCollimatorsToTrajectory": false,
			"shotgunDispersion": 0,
			"Chambers": [
				{
					"_name": "patron_in_weapon",
					"_id": "52432b8f2e5853f1efa02a8e",
					"_parent": "ed05294ed53c0400ae0e8a55",
					"_props": {
						"filters": [
							{
								"Filter": [
									"5fbe3ffdf8b6a877a729ea82",
									"5fd20ff893a8961fc660a954",
									"619636be6db0f2477964e710",
									"6196364158ef8c428c287d9f",
									"6196365d58ef8c428c287da1",
									"64b8725c4b75259c590fa899"
								]
							}
						]
					},
					"_required": false,
					"_mergeSlotWithChildren": false,
					"_proto": "55d4af244bdc2d962f8b4571"
				}
			]
		},
		"locales": {
			"en": {
				"name": "Kalashnikov AKS-74U .300 Blackout Assault Rifle",
				"shortName": "AKS-74U .300",
				"description": "A modified version of the Kalashnikov AKS-74U that is chambered in .300 blackout."
			}
		},
		"clearClonedProps": false,
		"addtoInventorySlots": [],
		"addtoModSlots": false,
		"modSlot": [],
		"ModdableItemWhitelist": [],
		"ModdableItemBlacklist": [],
		"fleaPriceRoubles": 29800,
		"handbookPriceRoubles": 13643,
		"addtoTraders": true,
		"traderId": "MECHANIC",
		"traderItems": [
			{
				"unlimitedCount": true,
				"stackObjectsCount": 99
			}
		],
		"barterScheme": [
			{
				"count": 26245,
				"_tpl": "ROUBLES"
			}
		],
		"loyallevelitems": 1,
		"addtoBots": false,
		"addtostaticlootcontainer": false,
		"StaticLootContainers": [
			{
				"ContainerName": "LOOTCONTAINER_WEAPON_BOX_4X4",
				"Probability": 250
			},
			{
				"ContainerName": "LOOTCONTAINER_DEAD_SCAV",
				"Probability": 150
			}
		],
		"masteries": true,
		"masterySections": [
			{
				"Name": "AKSU",
				"Templates": [
					"ed05294ed53c0400ae0e8a55"
				]
			}
		],
		"addweaponpreset": true,
		"weaponpresets": [
			{
				"_changeWeaponName": false,
				"_encyclopedia": "ed05294ed53c0400ae0e8a55",
				"_id": "660b23a0010010f388b90899",
				"_items": [
					{
						"_id": "9d2e8dbe412cac6757aeb145",
						"_tpl": "ed05294ed53c0400ae0e8a55",
						"upd": {
							"Repairable": {
								"MaxDurability": 100,
								"Durability": 100
							},
							"Foldable": {
								"Folded": false
							},
							"FireMode": {
								"FireMode": "single"
							}
						}
					},
					{
						"_id": "1808188b4e3c352df7bbf6a7",
						"_tpl": "57e3dba62459770f0c32322b",
						"parentId": "9d2e8dbe412cac6757aeb145",
						"slotId": "mod_pistol_grip"
					},
					{
						"_id": "98737cfc4db729413e571621",
						"_tpl": "5ac72e895acfc43b321d4bd5",
						"parentId": "9d2e8dbe412cac6757aeb145",
						"slotId": "mod_muzzle"
					},
					{
						"_id": "70b40009e99ad7b55836e852",
						"_tpl": "5ac66c5d5acfc4001718d314",
						"parentId": "9d2e8dbe412cac6757aeb145",
						"slotId": "mod_magazine"
					},
					{
						"_id": "d749c2192b47a6ce510ca514",
						"_tpl": "57dc347d245977596754e7a1",
						"parentId": "9d2e8dbe412cac6757aeb145",
						"slotId": "mod_stock"
					},
					{
						"_id": "71c802afb056b0e7dffa94c0",
						"_tpl": "57dc334d245977597164366f",
						"parentId": "9d2e8dbe412cac6757aeb145",
						"slotId": "mod_reciever"
					},
					{
						"_id": "2ab02660c45de8e04787ba37",
						"_tpl": "59d36a0086f7747e673f3946",
						"parentId": "9d2e8dbe412cac6757aeb145",
						"slotId": "mod_gas_block"
					},
					{
						"_id": "51b99b663d22bb6ecec2a068",
						"_tpl": "57dc32dc245977596d4ef3d3",
						"parentId": "2ab02660c45de8e04787ba37",
						"slotId": "mod_handguard"
					}
				],
				"_name": "AKS-74U .300 Stock preset",
				"_parent": "9d2e8dbe412cac6757aeb145",
				"_type": "Preset"
			}
		]
	},
	"ffc95b9d143f52202a311820": {
		"itemTplToClone": "5ac66d015acfc400180ae6e4",
		"parentId": "ASSAULT_RIFLE",
		"handbookParentId": "WEAPONS_ASSAULTRIFLES",
		"overrideProperties": {
			"Prefab": {
				"path": "assets/content/weapons/ak100/weapon_izhmash_ak102_556x45_container.bundle",
				"rcid": ""
			},
			"ConflictingItems": [
				"5b800e9286f7747a8b04f3ff",
				"5b80242286f77429445e0b47",
				"5c9a07572e221644f31c4b32",
				"5c9a1c3a2e2216000e69fb6a",
				"5c9a1c422e221600106f69f0",
				"5c17664f2e2216398b5a7e3c",
				"5a9d6d34a2750c00141e07da",
				"59fb375986f7741b681b81a6",
				"5a7dbfc1159bd40016548fde"
			],
			"Slots": [
				{
					"_name": "mod_gas_block",
					"_id": "7749297c426513a954aa69fe",
					"_parent": "ffc95b9d143f52202a311820",
					"_props": {
						"filters": [
							{
								"Shift": 0,
								"Filter": [
									"59c6633186f7740cf0493bb9",
									"59d64ec286f774171d1e0a42",
									"59e649f986f77411d949b246",
									"59ccfdba86f7747f2109a587",
									"726928d910aacf0b1b40b934",
									"eebec7fdda3d612c25d48af6",
									"4da17d6e133487626488aa2d",
									"f896348f6bab6164ae6e0c2e",
									"4c467c02973c90a5284cb89a"
								]
							}
						]
					},
					"_required": true,
					"_mergeSlotWithChildren": false,
					"_proto": "55d30c4c4bdc2db4468b457e"
				},
				{
					"_name": "mod_muzzle",
					"_id": "470528e13d89bd4f0bc3a62c",
					"_parent": "ffc95b9d143f52202a311820",
					"_props": {
						"filters": [
							{
								"Shift": 0,
								"Filter": [
									"5ac72e7d5acfc40016339a02",
									"5ac72e895acfc43b321d4bd5",
									"5f633f791b231926f2329f13",
									"5a9ea27ca2750c00137fa672",
									"5cc9ad73d7f00c000e2579d4",
									"5649ab884bdc2ded0b8b457f",
									"59bffc1f86f77435b128b872",
									"5e208b9842457a4a7a33d074",
									"5a0d63621526d8dba31fe3bf",
									"59fb257e86f7742981561852",
									"5a9fbacda2750c00141e080f",
									"65f119212ffe657478130322",
									"46cd26d8aff75c3562a031e5"
								]
							}
						]
					},
					"_required": false,
					"_mergeSlotWithChildren": false,
					"_proto": "55d30c4c4bdc2db4468b457e"
				},
				{
					"_name": "mod_pistol_grip",
					"_id": "9b0d7086f07d954527307c3e",
					"_parent": "ffc95b9d143f52202a311820",
					"_props": {
						"filters": [
							{
								"Shift": 0,
								"Filter": [
									"5f6341043ada5942720e2dc5",
									"6087e663132d4d12c81fd96b",
									"5beec8ea0db834001a6f9dbf",
									"5649ad3f4bdc2df8348b4585",
									"5649ade84bdc2d1b2b8b4587",
									"59e62cc886f77440d40b52a1",
									"5a0071d486f77404e23a12b2",
									"57e3dba62459770f0c32322b",
									"5cf54404d7f00c108840b2ef",
									"5e2192a498a36665e8337386",
									"5b30ac585acfc433000eb79c",
									"59e6318286f77444dd62c4cc",
									"5cf50850d7f00c056e24104c",
									"5cf508bfd7f00c056e24104e",
									"5947f92f86f77427344a76b1",
									"5947fa2486f77425b47c1a9b",
									"5c6bf4aa2e2216001219b0ae",
									"5649ae4a4bdc2d1b2b8b4588",
									"5998517986f7746017232f7e",
									"623c3be0484b5003161840dc",
									"628a664bccaab13006640e47",
									"628c9ab845c59e5b80768a81",
									"63f4da90f31d4a33b87bd054",
									"648ae3e356c6310a830fc291",
									"651580dc71a4f10aec4b6056"
								]
							}
						]
					},
					"_required": true,
					"_mergeSlotWithChildren": false,
					"_proto": "55d30c4c4bdc2db4468b457e"
				},
				{
					"_name": "mod_reciever",
					"_id": "b58a4ccb55ed4d0facc47764",
					"_parent": "ffc95b9d143f52202a311820",
					"_props": {
						"filters": [
							{
								"Shift": 0,
								"Filter": [
									"5649af094bdc2df8348b4586",
									"5ac50da15acfc4001718d287",
									"5d2c76ed48f03532f2136169",
									"5d2c770c48f0354b4a07c100",
									"5d2c772c48f0355d95672c25",
									"5649af884bdc2d1b2b8b4589",
									"628a665a86cbd9750d2ff5e5"
								]
							}
						]
					},
					"_required": false,
					"_mergeSlotWithChildren": false,
					"_proto": "55d30c4c4bdc2db4468b457e"
				},
				{
					"_name": "mod_sight_rear",
					"_id": "1d40f4aa2648e788005b7741",
					"_parent": "ffc95b9d143f52202a311820",
					"_props": {
						"filters": [
							{
								"Shift": 0,
								"Filter": [
									"5ac733a45acfc400192630e2",
									"5649b0544bdc2d1b2b8b458a",
									"5ac72e475acfc400180ae6fe",
									"5649d9a14bdc2d79388b4580",
									"628a7b23b0f75035732dd565",
									"649ec2cec93611967b03495e",
									"5bf3f59f0db834001a6fa060"
								]
							}
						]
					},
					"_required": false,
					"_mergeSlotWithChildren": false,
					"_proto": "55d30c4c4bdc2db4468b457e"
				},
				{
					"_name": "mod_magazine",
					"_id": "ef632bef49a4d7923532e832",
					"_parent": "ffc95b9d143f52202a311820",
					"_props": {
						"filters": [
							{
								"AnimationIndex": -1,
								"Filter": [
									"5ac66c5d5acfc4001718d314",
									"5c0548ae0db834001966a3c2",
									"c9aeb745fc67045b814af837",
									"4656b02dbe4bfa4a3a9e6d40"
								]
							}
						]
					},
					"_required": false,
					"_mergeSlotWithChildren": false,
					"_proto": "55d30c394bdc2dae468b4577"
				},
				{
					"_name": "mod_stock",
					"_id": "8cc0fa783caa9706922415c4",
					"_parent": "ffc95b9d143f52202a311820",
					"_props": {
						"filters": [
							{
								"Shift": 0,
								"Filter": [
									"5ac50c185acfc400163398d4",
									"5cf50fc5d7f00c056c53f83c",
									"5ac78eaf5acfc4001926317a",
									"5beec8b20db834001961942a",
									"6386300124a1dc425c00577a",
									"649ec87d8007560a9001ab36",
									"185bbb4e20e87b9aec36b1d5",
									"df1d3bfbd9835563f1574809",
									"9d387502b50d1f4b0fb8b0ce"
								]
							}
						]
					}
				},
				{
					"_name": "mod_mount_000",
					"_id": "d997e59f1f6b76586ab4b1ca",
					"_parent": "ffc95b9d143f52202a311820",
					"_props": {
						"filters": [
							{
								"Shift": 0,
								"Filter": [
									"5947db3f86f77447880cf76f",
									"6113d6c3290d254f5e6b27db",
									"57486e672459770abd687134",
									"618a5d5852ecee1505530b2a",
									"5c82342f2e221644f31c060e",
									"576fd4ec2459777f0b518431",
									"5c82343a2e221644f31c0611",
									"5cf638cbd7f00c06595bc936",
									"5a7c74b3e899ef0014332c29",
									"591ee00d86f774592f7b841e",
									"5d0a29ead7ad1a0026013f27",
									"618a75c9a3884f56c957ca1b",
									"57acb6222459771ec34b5cb0",
									"5c61a40d2e2216001403158d",
									"5c90c3622e221601da359851",
									"638db77630c4240f9e06f8b6",
									"63d114019e35b334d82302f7",
									"6544d4187c5457729210d277"
								]
							}
						]
					},
					"_required": false,
					"_mergeSlotWithChildren": false,
					"_proto": "55d30c4c4bdc2db4468b457e"
				},
				{
					"_name": "mod_charge",
					"_id": "d997e59f1f6b76586ab4b1ca",
					"_parent": "ffc95b9d143f52202a311820",
					"_props": {
						"filters": [
							{
								"Shift": 0,
								"Filter": [
									"6130ca3fd92c473c77020dbd",
									"5648ac824bdc2ded0b8b457d"
								]
							}
						]
					},
					"_required": false,
					"_mergeSlotWithChildren": false,
					"_proto": "55d30c4c4bdc2db4468b457e"
				}
			],
			"ammoCaliber": "Caliber762x35",
			"defMagType": "5ac66c5d5acfc4001718d314",
			"defAmmo": "5fbe3ffdf8b6a877a729ea82",
			"AdjustCollimatorsToTrajectory": false,
			"shotgunDispersion": 0,
			"Chambers": [
				{
					"_name": "patron_in_weapon",
					"_id": "cec9e993f6e563cf5f56146b",
					"_parent": "ffc95b9d143f52202a311820",
					"_props": {
						"filters": [
							{
								"Filter": [
									"5fbe3ffdf8b6a877a729ea82",
									"5fd20ff893a8961fc660a954",
									"619636be6db0f2477964e710",
									"6196364158ef8c428c287d9f",
									"6196365d58ef8c428c287da1",
									"64b8725c4b75259c590fa899"
								]
							}
						]
					},
					"_required": false,
					"_mergeSlotWithChildren": false,
					"_proto": "55d4af244bdc2d962f8b4571"
				}
			]
		},
		"locales": {
			"en": {
				"name": "Kalashnikov AK-102 .300 Blackout assault rifle",
				"shortName": "AK-102 .300",
				"description": "A modified version of the Kalashnikov AK-102 that is chambered in .300 blackout."
			}
		},
		"clearClonedProps": false,
		"addtoInventorySlots": [],
		"addtoModSlots": false,
		"modSlot": [],
		"ModdableItemWhitelist": [],
		"ModdableItemBlacklist": [],
		"fleaPriceRoubles": 27525,
		"handbookPriceRoubles": 51648,
		"addtoTraders": true,
		"traderId": "MECHANIC",
		"traderItems": [
			{
				"unlimitedCount": true,
				"stackObjectsCount": 99
			}
		],
		"barterScheme": [
			{
				"count": 39525,
				"_tpl": "ROUBLES"
			}
		],
		"loyallevelitems": 3,
		"addtoBots": false,
		"addtostaticlootcontainer": false,
		"StaticLootContainers": [
			{
				"ContainerName": "LOOTCONTAINER_WEAPON_BOX_4X4",
				"Probability": 250
			},
			{
				"ContainerName": "LOOTCONTAINER_DEAD_SCAV",
				"Probability": 150
			}
		],
		"masteries": true,
		"masterySections": [
			{
				"Name": "AK74",
				"Templates": [
					"ffc95b9d143f52202a311820"
				]
			}
		],
		"addweaponpreset": true,
		"weaponpresets": [
			{
				"_changeWeaponName": false,
				"_encyclopedia": "ffc95b9d143f52202a311820",
				"_id": "660b2339010010f388611caa",
				"_items": [
					{
						"_id": "36a175ae7b270b31788c6a5e",
						"_tpl": "ffc95b9d143f52202a311820",
						"upd": {
							"Repairable": {
								"MaxDurability": 100,
								"Durability": 100
							},
							"Foldable": {
								"Folded": false
							},
							"FireMode": {
								"FireMode": "single"
							}
						}
					},
					{
						"_id": "9f253688dfbf19235103784c",
						"_tpl": "59c6633186f7740cf0493bb9",
						"parentId": "36a175ae7b270b31788c6a5e",
						"slotId": "mod_gas_block"
					},
					{
						"_id": "5d8f9312a91ba5e457e5db59",
						"_tpl": "5ac72e895acfc43b321d4bd5",
						"parentId": "36a175ae7b270b31788c6a5e",
						"slotId": "mod_muzzle"
					},
					{
						"_id": "4a795eeae33f757968fde4d9",
						"_tpl": "5649ade84bdc2d1b2b8b4587",
						"parentId": "36a175ae7b270b31788c6a5e",
						"slotId": "mod_pistol_grip"
					},
					{
						"_id": "f19e2ae3e95374030bd00d11",
						"_tpl": "5ac50da15acfc4001718d287",
						"parentId": "36a175ae7b270b31788c6a5e",
						"slotId": "mod_reciever"
					},
					{
						"_id": "feb5996e5a86d6942daf9919",
						"_tpl": "5649b0544bdc2d1b2b8b458a",
						"parentId": "36a175ae7b270b31788c6a5e",
						"slotId": "mod_sight_rear"
					},
					{
						"_id": "4f0fb7c6114d7262a28f0308",
						"_tpl": "5ac66c5d5acfc4001718d314",
						"parentId": "36a175ae7b270b31788c6a5e",
						"slotId": "mod_magazine"
					},
					{
						"_id": "b8e475dc1f7fd99d554944a2",
						"_tpl": "5ac50c185acfc400163398d4",
						"parentId": "36a175ae7b270b31788c6a5e",
						"slotId": "mod_stock"
					},
					{
						"_id": "1de9eb7b0d18a68f5a47dd02",
						"_tpl": "5648b1504bdc2d9d488b4584",
						"parentId": "9f253688dfbf19235103784c",
						"slotId": "mod_handguard"
					}
				],
				"_name": "AK-102 .300 Stock preset",
				"_parent": "36a175ae7b270b31788c6a5e",
				"_type": "Preset"
			}
		]
	},
	"93bcdfda236122e67c098847": {
		"itemTplToClone": "57dc2fa62459775949412633",
		"parentId": "ASSAULT_CARBINE",
		"handbookParentId": "WEAPONS_CARBINES",
		"overrideProperties": {
			"Prefab": {
				"path": "assets/content/weapons/aks74u/weapon_izhmash_aks74u_545x39_container.bundle",
				"rcid": ""
			},
			"RecoilForceBack": 383,
			"RecoilForceUp": 122,
			"weapFireType": [
				"single"
			],
			"Slots": [
				{
					"_name": "mod_pistol_grip",
					"_id": "8edf72ce40437ab848bb32b5",
					"_parent": "93bcdfda236122e67c098847",
					"_props": {
						"filters": [
							{
								"Shift": 0,
								"Filter": [
									"5f6341043ada5942720e2dc5",
									"6087e663132d4d12c81fd96b",
									"5beec8ea0db834001a6f9dbf",
									"5649ad3f4bdc2df8348b4585",
									"5649ade84bdc2d1b2b8b4587",
									"59e62cc886f77440d40b52a1",
									"5a0071d486f77404e23a12b2",
									"57e3dba62459770f0c32322b",
									"5cf54404d7f00c108840b2ef",
									"5e2192a498a36665e8337386",
									"5b30ac585acfc433000eb79c",
									"59e6318286f77444dd62c4cc",
									"5cf50850d7f00c056e24104c",
									"5cf508bfd7f00c056e24104e",
									"5947f92f86f77427344a76b1",
									"5947fa2486f77425b47c1a9b",
									"5c6bf4aa2e2216001219b0ae",
									"5649ae4a4bdc2d1b2b8b4588",
									"5998517986f7746017232f7e",
									"623c3be0484b5003161840dc",
									"628c9ab845c59e5b80768a81",
									"628a664bccaab13006640e47",
									"63f4da90f31d4a33b87bd054",
									"648ae3e356c6310a830fc291",
									"651580dc71a4f10aec4b6056"
								]
							}
						]
					},
					"_required": true,
					"_mergeSlotWithChildren": false,
					"_proto": "55d30c4c4bdc2db4468b457e"
				},
				{
					"_name": "mod_muzzle",
					"_id": "a48b2d2ea27253ef8b5f3237",
					"_parent": "93bcdfda236122e67c098847",
					"_props": {
						"filters": [
							{
								"Shift": 0,
								"Filter": [
									"5ac72e7d5acfc40016339a02",
									"5ac72e895acfc43b321d4bd5",
									"5f633f791b231926f2329f13",
									"5a9ea27ca2750c00137fa672",
									"5cc9ad73d7f00c000e2579d4",
									"5649ab884bdc2ded0b8b457f",
									"59bffc1f86f77435b128b872",
									"5e208b9842457a4a7a33d074",
									"5a0d63621526d8dba31fe3bf",
									"59fb257e86f7742981561852",
									"5a9fbacda2750c00141e080f",
									"46cd26d8aff75c3562a031e5",
									"65f119212ffe657478130322"
								]
							}
						]
					},
					"_required": false,
					"_mergeSlotWithChildren": false,
					"_proto": "55d30c4c4bdc2db4468b457e"
				},
				{
					"_name": "mod_charge",
					"_id": "6259dc53c5ae8386c56634e3",
					"_parent": "93bcdfda236122e67c098847",
					"_props": {
						"filters": [
							{
								"Shift": 0,
								"Filter": [
									"6130ca3fd92c473c77020dbd",
									"5648ac824bdc2ded0b8b457d"
								]
							}
						]
					},
					"_required": false,
					"_mergeSlotWithChildren": false,
					"_proto": "55d30c4c4bdc2db4468b457e"
				},
				{
					"_name": "mod_magazine",
					"_id": "f93df1da40eb0ac0c95e2c61",
					"_parent": "93bcdfda236122e67c098847",
					"_props": {
						"filters": [
							{
								"AnimationIndex": -1,
								"Filter": [
									"59e5d83b86f7745aed03d262",
									"5a01c29586f77474660c694c",
									"5ac66bea5acfc43b321d4aec",
									"59d625f086f774661516605d",
									"5b1fd4e35acfc40018633c39",
									"5a0060fc86f7745793204432",
									"59e5f5a486f7746c530b3ce2",
									"5b1fb3e15acfc4001637f068",
									"59d6272486f77466146386ff",
									"5e21a3c67e40bd02257a008a",
									"5cbdc23eae9215001136a407",
									"5c6175362e221600133e3b94",
									"59fafc5086f7740dbe19f6c3",
									"59fafc9386f774067d462453",
									"5cfe8010d7ad1a59283b14c6",
									"6272874a6c47bd74f92e2087",
									"64b9cf0ac12b9c38db26923a"
								]
							}
						]
					},
					"_required": false,
					"_mergeSlotWithChildren": false,
					"_proto": "55d30c394bdc2dae468b4577"
				},
				{
					"_name": "mod_stock",
					"_id": "f93df1da40eb0ac0c95e2c61",
					"_parent": "93bcdfda236122e67c098847",
					"_props": {
						"filters": [
							{
								"Shift": 0,
								"Filter": [
									"59ecc28286f7746d7a68aa8c",
									"5ab626e4d8ce87272e4c6e43",
									"57dc347d245977596754e7a1",
									"185bbb4e20e87b9aec36b1d5",
									"df1d3bfbd9835563f1574809",
									"9d387502b50d1f4b0fb8b0ce"
								]
							}
						]
					}
				},
				{
					"_name": "mod_reciever",
					"_id": "8d54746794ae7e579f6fba84",
					"_parent": "93bcdfda236122e67c098847",
					"_props": {
						"filters": [
							{
								"Shift": 0,
								"Filter": [
									"57dc334d245977597164366f",
									"5839a7742459773cf9693481",
									"655cb6b5d680a544f30607fa"
								]
							}
						]
					},
					"_required": false,
					"_mergeSlotWithChildren": false,
					"_proto": "55d30c4c4bdc2db4468b457e"
				},
				{
					"_name": "mod_gas_block",
					"_id": "65ae54a53f96c64db0c5e273",
					"_parent": "93bcdfda236122e67c098847",
					"_props": {
						"filters": [
							{
								"Shift": 0,
								"Filter": [
									"59d36a0086f7747e673f3946"
								]
							}
						]
					},
					"_required": true,
					"_mergeSlotWithChildren": false,
					"_proto": "55d30c4c4bdc2db4468b457e"
				}
			],
			"ammoCaliber": "Caliber762x39",
			"defMagType": "5ac66c5d5acfc4001718d314",
			"defAmmo": "5fbe3ffdf8b6a877a729ea82",
			"AdjustCollimatorsToTrajectory": false,
			"shotgunDispersion": 0,
			"Chambers": [
				{
					"_name": "patron_in_weapon",
					"_id": "a0aee1fc268fa12a2721c8d3",
					"_parent": "93bcdfda236122e67c098847",
					"_props": {
						"filters": [
							{
								"Filter": [
									"59e0d99486f7744a32234762",
									"59e4d3d286f774176a36250a",
									"5656d7c34bdc2d9d198b4587",
									"59e4cf5286f7741778269d8a",
									"59e4d24686f7741776641ac7",
									"601aa3d2b2bcb34913271e6d",
									"64b7af5a8532cf95ee0a0dbd",
									"64b7af434b75259c590fa893",
									"64b7af734b75259c590fa895"
								]
							}
						]
					},
					"_required": false,
					"_mergeSlotWithChildren": false,
					"_proto": "55d4af244bdc2d962f8b4571"
				}
			]
		},
		"locales": {
			"en": {
				"name": "Century Arms Draco 7.62x39 carbine",
				"shortName": "Draco",
				"description": "Imported from Romania by Century Arms, was likely brought here by a PMC. Absolutely a poor man's krink."
			}
		},
		"clearClonedProps": false,
		"addtoInventorySlots": [],
		"addtoModSlots": false,
		"modSlot": [],
		"ModdableItemWhitelist": [],
		"ModdableItemBlacklist": [],
		"fleaPriceRoubles": 20800,
		"handbookPriceRoubles": 10643,
		"addtoTraders": true,
		"traderId": "PEACEKEEPER",
		"traderItems": [
			{
				"unlimitedCount": true,
				"stackObjectsCount": 99
			}
		],
		"barterScheme": [
			{
				"count": 20000,
				"_tpl": "ROUBLES"
			}
		],
		"loyallevelitems": 1,
		"addtoBots": false,
		"addtostaticlootcontainer": false,
		"StaticLootContainers": [
			{
				"ContainerName": "LOOTCONTAINER_WEAPON_BOX_4X4",
				"Probability": 250
			},
			{
				"ContainerName": "LOOTCONTAINER_DEAD_SCAV",
				"Probability": 150
			}
		],
		"masteries": true,
		"masterySections": [
			{
				"Name": "AKM",
				"Templates": [
					"93bcdfda236122e67c098847"
				]
			}
		],
		"addweaponpreset": true,
		"weaponpresets": [
			{
				"_changeWeaponName": false,
				"_encyclopedia": "93bcdfda236122e67c098847",
				"_id": "660b4a90010010f388968e18",
				"_items": [
					{
						"_id": "76473c126cd112b5b585ae8b",
						"_tpl": "93bcdfda236122e67c098847",
						"upd": {
							"StackObjectsCount": 99,
							"Repairable": {
								"MaxDurability": 100,
								"Durability": 100
							},
							"Foldable": {
								"Folded": false
							},
							"FireMode": {
								"FireMode": "single"
							}
						}
					},
					{
						"_id": "2b255c348f41b1d435e83eed",
						"_tpl": "57e3dba62459770f0c32322b",
						"parentId": "76473c126cd112b5b585ae8b",
						"slotId": "mod_pistol_grip"
					},
					{
						"_id": "6e7c37b30d87020344b42dfd",
						"_tpl": "5ac72e895acfc43b321d4bd5",
						"parentId": "76473c126cd112b5b585ae8b",
						"slotId": "mod_muzzle"
					},
					{
						"_id": "00e6897fdf9b2609178f4252",
						"_tpl": "59d6272486f77466146386ff",
						"parentId": "76473c126cd112b5b585ae8b",
						"slotId": "mod_magazine"
					},
					{
						"_id": "6a9a8d44f2a75452b407cb46",
						"_tpl": "57dc347d245977596754e7a1",
						"parentId": "76473c126cd112b5b585ae8b",
						"slotId": "mod_stock"
					},
					{
						"_id": "e4b0200747760435445586dd",
						"_tpl": "57dc334d245977597164366f",
						"parentId": "76473c126cd112b5b585ae8b",
						"slotId": "mod_reciever"
					},
					{
						"_id": "48de431f7092d13944709eca",
						"_tpl": "59d36a0086f7747e673f3946",
						"parentId": "76473c126cd112b5b585ae8b",
						"slotId": "mod_gas_block"
					},
					{
						"_id": "d04e321c6824e6066d99b3ba",
						"_tpl": "57dc32dc245977596d4ef3d3",
						"parentId": "48de431f7092d13944709eca",
						"slotId": "mod_handguard"
					}
				],
				"_name": "Century Arms Draco Stock preset",
				"_parent": "76473c126cd112b5b585ae8b",
				"_type": "Preset"
			}
		]
	},
	"57f28a7ffb22e277b0234219": {
		"itemTplToClone": "5644bd2b4bdc2d3b4c8b4572",
		"parentId": "ASSAULT_CARBINE",
		"handbookParentId": "WEAPONS_CARBINES",
		"overrideProperties": {
			"Prefab": {
				"path": "assets/content/weapons/ak74/weapon_izhmash_ak74n_545x39_container.bundle",
				"rcid": ""
			},
			"weapFireType": [
				"single"
			]
		},
		"locales": {
			"en": {
				"name": "Saiga SGL31 5.45x39 Carbine",
				"shortName": "Saiga 545",
				"description": "Produced by Saiga out of the Izhmash factory as a civilian version of the AK-74N. Semi automatic only, factory fitted with a 10 round magazine."
			}
		},
		"clearClonedProps": false,
		"addtoInventorySlots": [],
		"addtoModSlots": false,
		"modSlot": [],
		"ModdableItemWhitelist": [],
		"ModdableItemBlacklist": [],
		"fleaPriceRoubles": 20800,
		"handbookPriceRoubles": 10643,
		"addtoTraders": true,
		"traderId": "SKIER",
		"traderItems": [
			{
				"unlimitedCount": true,
				"stackObjectsCount": 99
			}
		],
		"barterScheme": [
			{
				"count": 24600,
				"_tpl": "ROUBLES"
			}
		],
		"loyallevelitems": 1,
		"addtoBots": false,
		"addtostaticlootcontainer": false,
		"StaticLootContainers": [
			{
				"ContainerName": "LOOTCONTAINER_WEAPON_BOX_4X4",
				"Probability": 250
			},
			{
				"ContainerName": "LOOTCONTAINER_DEAD_SCAV",
				"Probability": 150
			}
		],
		"masteries": true,
		"masterySections": [
			{
				"Name": "AK74",
				"Templates": [
					"57f28a7ffb22e277b0234219"
				]
			}
		],
		"addweaponpreset": true,
		"weaponpresets": [
			{
				"_changeWeaponName": false,
				"_encyclopedia": "57f28a7ffb22e277b0234219",
				"_id": "660b56ee010010f388ccbe34",
				"_items": [
					{
						"_id": "318f01040a4f2ecd57e1f08e",
						"_tpl": "57f28a7ffb22e277b0234219",
						"upd": {
							"StackObjectsCount": 99,
							"Repairable": {
								"MaxDurability": 100,
								"Durability": 100
							},
							"FireMode": {
								"FireMode": "single"
							}
						}
					},
					{
						"_id": "c446bee44fafd11d4b94ff9a",
						"_tpl": "59c6633186f7740cf0493bb9",
						"parentId": "318f01040a4f2ecd57e1f08e",
						"slotId": "mod_gas_block"
					},
					{
						"_id": "23897635ba082217a8c18e15",
						"_tpl": "5ac7655e5acfc40016339a19",
						"parentId": "318f01040a4f2ecd57e1f08e",
						"slotId": "mod_muzzle"
					},
					{
						"_id": "18e5a10e9daac60d938ed60c",
						"_tpl": "5649ade84bdc2d1b2b8b4587",
						"parentId": "318f01040a4f2ecd57e1f08e",
						"slotId": "mod_pistol_grip"
					},
					{
						"_id": "12012708d42cf48f5f6e16d4",
						"_tpl": "5ac50da15acfc4001718d287",
						"parentId": "318f01040a4f2ecd57e1f08e",
						"slotId": "mod_reciever"
					},
					{
						"_id": "bbc87b1e1439012b0ffc063a",
						"_tpl": "5ac72e475acfc400180ae6fe",
						"parentId": "318f01040a4f2ecd57e1f08e",
						"slotId": "mod_sight_rear"
					},
					{
						"_id": "b17d0cd35186d1ae3223c97b",
						"_tpl": "5649b0fc4bdc2d17108b4588",
						"parentId": "318f01040a4f2ecd57e1f08e",
						"slotId": "mod_stock"
					},
					{
						"_id": "deb40d58824d4df8a1f050b1",
						"_tpl": "55d4837c4bdc2d1d4e8b456c",
						"parentId": "318f01040a4f2ecd57e1f08e",
						"slotId": "mod_magazine"
					},
					{
						"_id": "92e2613886d97daf667f4da2",
						"_tpl": "5648b1504bdc2d9d488b4584",
						"parentId": "c446bee44fafd11d4b94ff9a",
						"slotId": "mod_handguard"
					}
				],
				"_name": "Saiga SGL31 Stock preset",
				"_parent": "318f01040a4f2ecd57e1f08e",
				"_type": "Preset"
			}
		]
	},
	"e895575bcd1fa1de36d301b6": {
		"itemTplToClone": "5ac4cd105acfc40016339859",
		"parentId": "ASSAULT_CARBINE",
		"handbookParentId": "WEAPONS_CARBINES",
		"overrideProperties": {
			"Prefab": {
				"path": "assets/content/weapons/ak74m/weapon_izhmash_ak74m_545x39_container.bundle",
				"rcid": ""
			},
			"weapFireType": [
				"single"
			]
		},
		"locales": {
			"en": {
				"name": "Saiga MK Ver. 030 5.45x39 Carbine",
				"shortName": "Saiga MK 545",
				"description": "The Saiga-MK self-loading carbine is patterned after the AK74M Kalashnikov rifle. Its 030 version has a removable muzzle brake, sight leaf and an index-finger-adapted safety lock. -Export agency"
			}
		},
		"clearClonedProps": false,
		"addtoInventorySlots": [],
		"addtoModSlots": false,
		"modSlot": [],
		"ModdableItemWhitelist": [],
		"ModdableItemBlacklist": [],
		"fleaPriceRoubles": 22800,
		"handbookPriceRoubles": 10643,
		"addtoTraders": true,
		"traderId": "SKIER",
		"traderItems": [
			{
				"unlimitedCount": true,
				"stackObjectsCount": 99
			}
		],
		"barterScheme": [
			{
				"count": 27600,
				"_tpl": "ROUBLES"
			}
		],
		"loyallevelitems": 1,
		"addtoBots": false,
		"addtostaticlootcontainer": false,
		"StaticLootContainers": [
			{
				"ContainerName": "LOOTCONTAINER_WEAPON_BOX_4X4",
				"Probability": 250
			},
			{
				"ContainerName": "LOOTCONTAINER_DEAD_SCAV",
				"Probability": 150
			}
		],
		"masteries": true,
		"masterySections": [
			{
				"Name": "AK74",
				"Templates": [
					"e895575bcd1fa1de36d301b6"
				]
			}
		],
		"addweaponpreset": true,
		"weaponpresets": [
			{
				"_changeWeaponName": false,
				"_encyclopedia": "e895575bcd1fa1de36d301b6",
				"_id": "660b566e010010f3889ce04d",
				"_items": [
					{
						"_id": "115ca75a55b2823f7b6d9e3c",
						"_tpl": "e895575bcd1fa1de36d301b6",
						"upd": {
							"StackObjectsCount": 99,
							"Repairable": {
								"MaxDurability": 100,
								"Durability": 100
							},
							"Foldable": {
								"Folded": false
							},
							"FireMode": {
								"FireMode": "single"
							}
						}
					},
					{
						"_id": "20ef697eb1a81868e3accd4b",
						"_tpl": "59c6633186f7740cf0493bb9",
						"parentId": "115ca75a55b2823f7b6d9e3c",
						"slotId": "mod_gas_block"
					},
					{
						"_id": "4587264be9d051295de83ff9",
						"_tpl": "5ac7655e5acfc40016339a19",
						"parentId": "115ca75a55b2823f7b6d9e3c",
						"slotId": "mod_muzzle"
					},
					{
						"_id": "1db8b5b95f713208261e50a9",
						"_tpl": "5649ade84bdc2d1b2b8b4587",
						"parentId": "115ca75a55b2823f7b6d9e3c",
						"slotId": "mod_pistol_grip"
					},
					{
						"_id": "2897e28c972f11f7f8ba3ce5",
						"_tpl": "5ac50da15acfc4001718d287",
						"parentId": "115ca75a55b2823f7b6d9e3c",
						"slotId": "mod_reciever"
					},
					{
						"_id": "57f5e273e37b8fbf1b9098f6",
						"_tpl": "5ac72e475acfc400180ae6fe",
						"parentId": "115ca75a55b2823f7b6d9e3c",
						"slotId": "mod_sight_rear"
					},
					{
						"_id": "c1fd83ff59aac19854532937",
						"_tpl": "5ac50c185acfc400163398d4",
						"parentId": "115ca75a55b2823f7b6d9e3c",
						"slotId": "mod_stock"
					},
					{
						"_id": "2f14be89b3b1efc59ae84ccd",
						"_tpl": "55d480c04bdc2d1d4e8b456a",
						"parentId": "115ca75a55b2823f7b6d9e3c",
						"slotId": "mod_magazine"
					},
					{
						"_id": "6b8a6f2f47025f6cd9c28501",
						"_tpl": "5cbda392ae92155f3c17c39f",
						"parentId": "20ef697eb1a81868e3accd4b",
						"slotId": "mod_handguard"
					}
				],
				"_name": "Saiga MK Ver. 030 Stock preset",
				"_parent": "115ca75a55b2823f7b6d9e3c",
				"_type": "Preset"
			}
		]
	},
	"3dc691f607ffed3228bf6ca2": {
		"itemTplToClone": "6499849fc93611967b034949",
		"parentId": "ASSAULT_RIFLE",
		"handbookParentId": "WEAPONS_ASSAULTRIFLES",
		"overrideProperties": {
			"Prefab": {
				"path": "assets/content/weapons/ak12/weapon_izhmash_ak12_545x39_container.bundle",
				"rcid": ""
			},
			"RecoilForceBack": 328,
			"RecoilForceUp": 115,
			"Slots": [
				{
					"_name": "mod_gas_block",
					"_id": "6499849fc93611967b03494b",
					"_parent": "6499849fc93611967b034949",
					"_props": {
						"filters": [
							{
								"Shift": 0,
								"Filter": [
									"649ec107961514b22506b10c"
								]
							}
						]
					},
					"_required": true,
					"_mergeSlotWithChildren": false,
					"_proto": "55d30c4c4bdc2db4468b457e"
				},
				{
					"_name": "mod_launcher",
					"_id": "6499849fc93611967b03494c",
					"_parent": "6499849fc93611967b034949",
					"_props": {
						"filters": [
							{
								"Shift": 0,
								"Filter": [
									"5648b62b4bdc2d9d488b4585",
									"62e7e7bbe6da9612f743f1e0"
								]
							}
						]
					},
					"_required": false,
					"_mergeSlotWithChildren": false,
					"_proto": "55d30c4c4bdc2db4468b457e"
				},
				{
					"_name": "mod_muzzle",
					"_id": "6499849fc93611967b03494d",
					"_parent": "6499849fc93611967b034949",
					"_props": {
						"filters": [
							{
								"Shift": 0,
								"Filter": [
									"dd6b29946db0932ea75e09c4",
									"43b167b7a5c61d36f59f0783"
								]
							}
						]
					},
					"_required": false,
					"_mergeSlotWithChildren": false,
					"_proto": "55d30c4c4bdc2db4468b457e"
				},
				{
					"_name": "mod_pistol_grip",
					"_id": "6499849fc93611967b03494e",
					"_parent": "6499849fc93611967b034949",
					"_props": {
						"filters": [
							{
								"Shift": 0,
								"Filter": [
									"5f6341043ada5942720e2dc5",
									"6087e663132d4d12c81fd96b",
									"623c3be0484b5003161840dc",
									"5beec8ea0db834001a6f9dbf",
									"5649ad3f4bdc2df8348b4585",
									"5649ade84bdc2d1b2b8b4587",
									"59e62cc886f77440d40b52a1",
									"5a0071d486f77404e23a12b2",
									"57e3dba62459770f0c32322b",
									"5cf54404d7f00c108840b2ef",
									"5e2192a498a36665e8337386",
									"5b30ac585acfc433000eb79c",
									"59e6318286f77444dd62c4cc",
									"5cf50850d7f00c056e24104c",
									"5cf508bfd7f00c056e24104e",
									"628a664bccaab13006640e47",
									"628c9ab845c59e5b80768a81",
									"5947f92f86f77427344a76b1",
									"5947fa2486f77425b47c1a9b",
									"5c6bf4aa2e2216001219b0ae",
									"5649ae4a4bdc2d1b2b8b4588",
									"5998517986f7746017232f7e",
									"63f4da90f31d4a33b87bd054",
									"648ae3e356c6310a830fc291",
									"651580dc71a4f10aec4b6056"
								]
							}
						]
					},
					"_required": true,
					"_mergeSlotWithChildren": false,
					"_proto": "55d30c4c4bdc2db4468b457e"
				},
				{
					"_name": "mod_reciever",
					"_id": "6499849fc93611967b03494f",
					"_parent": "6499849fc93611967b034949",
					"_props": {
						"filters": [
							{
								"Shift": 0,
								"Filter": [
									"649ec2f3961514b22506b111"
								]
							}
						]
					},
					"_required": false,
					"_mergeSlotWithChildren": false,
					"_proto": "55d30c4c4bdc2db4468b457e"
				},
				{
					"_name": "mod_stock_001",
					"_id": "6499849fc93611967b034951",
					"_parent": "6499849fc93611967b034949",
					"_props": {
						"filters": [
							{
								"Shift": 0,
								"Filter": [
									"5ac50c185acfc400163398d4",
									"5cf50fc5d7f00c056c53f83c",
									"5beec8b20db834001961942a",
									"6386300124a1dc425c00577a",
									"649ec87d8007560a9001ab36",
									"9d387502b50d1f4b0fb8b0ce"
								]
							}
						]
					},
					"_required": false,
					"_mergeSlotWithChildren": false,
					"_proto": "55d30c4c4bdc2db4468b457e"
				},
				{
					"_name": "mod_magazine",
					"_id": "6499849fc93611967b034952",
					"_parent": "6499849fc93611967b034949",
					"_props": {
						"filters": [
							{
								"AnimationIndex": -1,
								"Filter": [
									"59e5d83b86f7745aed03d262",
									"5a01c29586f77474660c694c",
									"5ac66bea5acfc43b321d4aec",
									"59d625f086f774661516605d",
									"5b1fd4e35acfc40018633c39",
									"5a0060fc86f7745793204432",
									"59e5f5a486f7746c530b3ce2",
									"5b1fb3e15acfc4001637f068",
									"59d6272486f77466146386ff",
									"5e21a3c67e40bd02257a008a",
									"5cbdc23eae9215001136a407",
									"5c6175362e221600133e3b94",
									"59fafc5086f7740dbe19f6c3",
									"59fafc9386f774067d462453",
									"5cfe8010d7ad1a59283b14c6",
									"6272874a6c47bd74f92e2087",
									"64b9cf0ac12b9c38db26923a"
								]
							}
						]
					},
					"_required": false,
					"_mergeSlotWithChildren": false,
					"_proto": "55d30c394bdc2dae468b4577"
				},
				{
					"_name": "mod_charge",
					"_id": "6499849fc93611967b034954",
					"_parent": "6499849fc93611967b034949",
					"_props": {
						"filters": [
							{
								"Shift": 0,
								"Filter": [
									"6130ca3fd92c473c77020dbd",
									"5648ac824bdc2ded0b8b457d"
								]
							}
						]
					},
					"_required": false,
					"_mergeSlotWithChildren": false,
					"_proto": "55d30c4c4bdc2db4468b457e"
				},
				{
					"_name": "mod_handguard",
					"_id": "649ed407b013f04a700e60fe",
					"_parent": "6499849fc93611967b034949",
					"_props": {
						"filters": [
							{
								"Shift": 0,
								"Filter": [
									"649ec127c93611967b034957"
								]
							}
						]
					},
					"_required": true,
					"_mergeSlotWithChildren": false,
					"_proto": "55d30c4c4bdc2db4468b457e"
				}
			],
			"ammoCaliber": "Caliber762x39",
			"defMagType": "59d625f086f774661516605d",
			"defAmmo": "5656d7c34bdc2d9d198b4587",
			"Chambers": [
				{
					"_name": "patron_in_weapon",
					"_id": "9efa2df053e734a66c8da122",
					"_parent": "3dc691f607ffed3228bf6ca2",
					"_props": {
						"filters": [
							{
								"Filter": [
									"59e0d99486f7744a32234762",
									"59e4d3d286f774176a36250a",
									"5656d7c34bdc2d9d198b4587",
									"59e4cf5286f7741778269d8a",
									"59e4d24686f7741776641ac7",
									"601aa3d2b2bcb34913271e6d",
									"64b7af5a8532cf95ee0a0dbd",
									"64b7af434b75259c590fa893",
									"64b7af734b75259c590fa895"
								]
							}
						]
					},
					"_required": false,
					"_mergeSlotWithChildren": false,
					"_proto": "55d4af244bdc2d962f8b4571"
				}
			]
		},
		"locales": {
			"en": {
				"name": "Kalashnikov AK-15 7.62x39 assault rifle",
				"shortName": "AK-15",
				"description": "The 7.62 mm AK-15 is an assault rifle used by the special operations units of the Russian military and other law enforcement agencies. The AK-15 is part of the Ratnik equipment kit."
			}
		},
		"clearClonedProps": false,
		"addtoInventorySlots": [],
		"addtoModSlots": false,
		"modSlot": [],
		"ModdableItemWhitelist": [],
		"ModdableItemBlacklist": [],
		"fleaPriceRoubles": 62544,
		"handbookPriceRoubles": 49520,
		"addtoTraders": true,
		"traderId": "PRAPOR",
		"traderItems": [
			{
				"unlimitedCount": true,
				"stackObjectsCount": 99
			}
		],
		"barterScheme": [
			{
				"count": 92200,
				"_tpl": "ROUBLES"
			}
		],
		"loyallevelitems": 4,
		"addtoBots": false,
		"addtostaticlootcontainer": false,
		"StaticLootContainers": [
			{
				"ContainerName": "LOOTCONTAINER_WEAPON_BOX_4X4",
				"Probability": 250
			},
			{
				"ContainerName": "LOOTCONTAINER_DEAD_SCAV",
				"Probability": 150
			}
		],
		"masteries": true,
		"masterySections": [
			{
				"Name": "AK74",
				"Templates": [
					"93bcdfda236122e67c098847"
				]
			}
		],
		"addweaponpreset": false,
		"weaponpresets": [
			{
				"_changeWeaponName": false,
				"_encyclopedia": "93bcdfda236122e67c098847",
				"_id": "660b4a90010010f388968e18",
				"_items": [
					{
						"_id": "76473c126cd112b5b585ae8b",
						"_tpl": "93bcdfda236122e67c098847",
						"upd": {
							"StackObjectsCount": 99,
							"Repairable": {
								"MaxDurability": 100,
								"Durability": 100
							},
							"Foldable": {
								"Folded": false
							},
							"FireMode": {
								"FireMode": "single"
							}
						}
					},
					{
						"_id": "2b255c348f41b1d435e83eed",
						"_tpl": "57e3dba62459770f0c32322b",
						"parentId": "76473c126cd112b5b585ae8b",
						"slotId": "mod_pistol_grip"
					},
					{
						"_id": "6e7c37b30d87020344b42dfd",
						"_tpl": "5ac72e895acfc43b321d4bd5",
						"parentId": "76473c126cd112b5b585ae8b",
						"slotId": "mod_muzzle"
					},
					{
						"_id": "00e6897fdf9b2609178f4252",
						"_tpl": "59d6272486f77466146386ff",
						"parentId": "76473c126cd112b5b585ae8b",
						"slotId": "mod_magazine"
					},
					{
						"_id": "6a9a8d44f2a75452b407cb46",
						"_tpl": "57dc347d245977596754e7a1",
						"parentId": "76473c126cd112b5b585ae8b",
						"slotId": "mod_stock"
					},
					{
						"_id": "e4b0200747760435445586dd",
						"_tpl": "57dc334d245977597164366f",
						"parentId": "76473c126cd112b5b585ae8b",
						"slotId": "mod_reciever"
					},
					{
						"_id": "48de431f7092d13944709eca",
						"_tpl": "59d36a0086f7747e673f3946",
						"parentId": "76473c126cd112b5b585ae8b",
						"slotId": "mod_gas_block"
					},
					{
						"_id": "d04e321c6824e6066d99b3ba",
						"_tpl": "57dc32dc245977596d4ef3d3",
						"parentId": "48de431f7092d13944709eca",
						"slotId": "mod_handguard"
					}
				],
				"_name": "Century Arms Draco Stock preset",
				"_parent": "76473c126cd112b5b585ae8b",
				"_type": "Preset"
			}
		]
	},
	"52500592c7109667abb6cbeb": {
		"itemTplToClone": "583990e32459771419544dd2",
		"parentId": "ASSAULT_RIFLE",
		"handbookParentId": "WEAPONS_ASSAULTRIFLES",
		"overrideProperties": {
			"Prefab": {
				"path": "assets/content/weapons/aks74u/weapon_izhmash_aks74ub_545x39_container.bundle",
				"rcid": ""
			},
			"RecoilForceBack": 369,
			"RecoilForceUp": 111,
			"Slots": [
				{
					"_name": "mod_pistol_grip",
					"_id": "be3c51742bd2f6a327ccd04c",
					"_parent": "52500592c7109667abb6cbeb",
					"_props": {
						"filters": [
							{
								"Shift": 0,
								"Filter": [
									"5f6341043ada5942720e2dc5",
									"6087e663132d4d12c81fd96b",
									"5beec8ea0db834001a6f9dbf",
									"5649ad3f4bdc2df8348b4585",
									"5649ade84bdc2d1b2b8b4587",
									"59e62cc886f77440d40b52a1",
									"5a0071d486f77404e23a12b2",
									"57e3dba62459770f0c32322b",
									"5cf54404d7f00c108840b2ef",
									"5e2192a498a36665e8337386",
									"5b30ac585acfc433000eb79c",
									"59e6318286f77444dd62c4cc",
									"5cf50850d7f00c056e24104c",
									"5cf508bfd7f00c056e24104e",
									"5947f92f86f77427344a76b1",
									"5947fa2486f77425b47c1a9b",
									"5c6bf4aa2e2216001219b0ae",
									"5649ae4a4bdc2d1b2b8b4588",
									"5998517986f7746017232f7e",
									"623c3be0484b5003161840dc",
									"628a664bccaab13006640e47",
									"628c9ab845c59e5b80768a81",
									"63f4da90f31d4a33b87bd054",
									"648ae3e356c6310a830fc291",
									"651580dc71a4f10aec4b6056"
								]
							}
						]
					},
					"_required": true,
					"_mergeSlotWithChildren": false,
					"_proto": "55d30c4c4bdc2db4468b457e"
				},
				{
					"_name": "mod_charge",
					"_id": "1b9746298c1ccf5d8b24eb81",
					"_parent": "52500592c7109667abb6cbeb",
					"_props": {
						"filters": [
							{
								"Shift": 0,
								"Filter": [
									"6130ca3fd92c473c77020dbd",
									"5648ac824bdc2ded0b8b457d"
								]
							}
						]
					},
					"_required": false,
					"_mergeSlotWithChildren": false,
					"_proto": "55d30c4c4bdc2db4468b457e"
				},
				{
					"_name": "mod_muzzle",
					"_id": "3ef7f856ba4aab773e2ef50b",
					"_parent": "52500592c7109667abb6cbeb",
					"_props": {
						"filters": [
							{
								"Shift": 0,
								"Filter": [
									"5ac72e7d5acfc40016339a02",
									"5ac72e895acfc43b321d4bd5",
									"5f633f791b231926f2329f13",
									"5a9ea27ca2750c00137fa672",
									"5cc9ad73d7f00c000e2579d4",
									"5649ab884bdc2ded0b8b457f",
									"59bffc1f86f77435b128b872",
									"5e208b9842457a4a7a33d074",
									"5a0d63621526d8dba31fe3bf",
									"59fb257e86f7742981561852",
									"5a9fbacda2750c00141e080f",
									"65f119212ffe657478130322",
									"46cd26d8aff75c3562a031e5"
								]
							}
						]
					},
					"_required": false,
					"_mergeSlotWithChildren": false,
					"_proto": "55d30c4c4bdc2db4468b457e"
				},
				{
					"_name": "mod_magazine",
					"_id": "b303e7c69c8ab92d33068993",
					"_parent": "52500592c7109667abb6cbeb",
					"_props": {
						"filters": [
							{
								"AnimationIndex": -1,
								"Filter": [
									"59e5d83b86f7745aed03d262",
									"5a01c29586f77474660c694c",
									"5ac66bea5acfc43b321d4aec",
									"59d625f086f774661516605d",
									"5b1fd4e35acfc40018633c39",
									"5a0060fc86f7745793204432",
									"59e5f5a486f7746c530b3ce2",
									"5b1fb3e15acfc4001637f068",
									"59d6272486f77466146386ff",
									"5e21a3c67e40bd02257a008a",
									"5cbdc23eae9215001136a407",
									"5c6175362e221600133e3b94",
									"59fafc5086f7740dbe19f6c3",
									"59fafc9386f774067d462453",
									"5cfe8010d7ad1a59283b14c6",
									"6272874a6c47bd74f92e2087",
									"64b9cf0ac12b9c38db26923a"
								]
							}
						]
					},
					"_required": false,
					"_mergeSlotWithChildren": false,
					"_proto": "55d30c394bdc2dae468b4577"
				},
				{
					"_name": "mod_stock",
					"_id": "cf43ef162c5f15fa2473a6b4",
					"_parent": "52500592c7109667abb6cbeb",
					"_props": {
						"filters": [
							{
								"Shift": 0,
								"Filter": [
									"59ecc28286f7746d7a68aa8c",
									"5ab626e4d8ce87272e4c6e43",
									"57dc347d245977596754e7a1",
									"185bbb4e20e87b9aec36b1d5",
									"df1d3bfbd9835563f1574809",
									"9d387502b50d1f4b0fb8b0ce"
								]
							}
						]
					}
				},
				{
					"_name": "mod_reciever",
					"_id": "d1929bed11ae9d891f8fd1b5",
					"_parent": "52500592c7109667abb6cbeb",
					"_props": {
						"filters": [
							{
								"Shift": 0,
								"Filter": [
									"57dc334d245977597164366f",
									"5839a7742459773cf9693481",
									"655cb6b5d680a544f30607fa"
								]
							}
						]
					},
					"_required": false,
					"_mergeSlotWithChildren": false,
					"_proto": "55d30c4c4bdc2db4468b457e"
				},
				{
					"_name": "mod_mount_000",
					"_id": "e8b83ec99efa511b8b61dedc",
					"_parent": "52500592c7109667abb6cbeb",
					"_props": {
						"filters": [
							{
								"Shift": 0,
								"Filter": [
									"5947db3f86f77447880cf76f",
									"6113d6c3290d254f5e6b27db",
									"57486e672459770abd687134",
									"618a5d5852ecee1505530b2a",
									"5c82342f2e221644f31c060e",
									"576fd4ec2459777f0b518431",
									"5c82343a2e221644f31c0611",
									"5cf638cbd7f00c06595bc936",
									"5a7c74b3e899ef0014332c29",
									"591ee00d86f774592f7b841e",
									"5d0a29ead7ad1a0026013f27",
									"618a75c9a3884f56c957ca1b",
									"57acb6222459771ec34b5cb0",
									"5c61a40d2e2216001403158d",
									"5c90c3622e221601da359851",
									"638db77630c4240f9e06f8b6",
									"63d114019e35b334d82302f7",
									"6544d4187c5457729210d277"
								]
							}
						]
					},
					"_required": false,
					"_mergeSlotWithChildren": false,
					"_proto": "55d30c4c4bdc2db4468b457e"
				},
				{
					"_name": "mod_gas_block",
					"_id": "15eb020b1f8765da42633073",
					"_parent": "52500592c7109667abb6cbeb",
					"_props": {
						"filters": [
							{
								"Shift": 0,
								"Filter": [
									"59d36a0086f7747e673f3946"
								]
							}
						]
					},
					"_required": true,
					"_mergeSlotWithChildren": false,
					"_proto": "55d30c4c4bdc2db4468b457e"
				}
			],
			"ammoCaliber": "Caliber762x39",
			"defMagType": "5ac66c5d5acfc4001718d314",
			"defAmmo": "5fbe3ffdf8b6a877a729ea82",
			"AdjustCollimatorsToTrajectory": false,
			"shotgunDispersion": 0,
			"Chambers": [
				{
					"_name": "patron_in_weapon",
					"_id": "a0aee1fc268fa12a2721c8d3",
					"_parent": "93bcdfda236122e67c098847",
					"_props": {
						"filters": [
							{
								"Filter": [
									"59e0d99486f7744a32234762",
									"59e4d3d286f774176a36250a",
									"5656d7c34bdc2d9d198b4587",
									"59e4cf5286f7741778269d8a",
									"59e4d24686f7741776641ac7",
									"601aa3d2b2bcb34913271e6d",
									"64b7af5a8532cf95ee0a0dbd",
									"64b7af434b75259c590fa893",
									"64b7af734b75259c590fa895"
								]
							}
						]
					},
					"_required": false,
					"_mergeSlotWithChildren": false,
					"_proto": "55d4af244bdc2d962f8b4571"
				}
			]
		},
		"locales": {
			"en": {
				"name": "Modified Century Arms Draco 7.62x39 Assault Rifle",
				"shortName": "Draco",
				"description": "A Century arms Draco, modified expertly by badger for full auto fire and a dovetail mount."
			}
		},
		"clearClonedProps": false,
		"addtoInventorySlots": [],
		"addtoModSlots": false,
		"modSlot": [],
		"ModdableItemWhitelist": [],
		"ModdableItemBlacklist": [],
		"fleaPriceRoubles": 20800,
		"handbookPriceRoubles": 10643,
		"addtoTraders": true,
		"traderId": "BADGER",
		"traderItems": [
			{
				"unlimitedCount": true,
				"stackObjectsCount": 99
			}
		],
		"barterScheme": [
			{
				"count": 340,
				"_tpl": "DOLLARS"
			}
		],
		"loyallevelitems": 3,
		"addtoBots": false,
		"addtostaticlootcontainer": false,
		"StaticLootContainers": [
			{
				"ContainerName": "LOOTCONTAINER_WEAPON_BOX_4X4",
				"Probability": 250
			},
			{
				"ContainerName": "LOOTCONTAINER_DEAD_SCAV",
				"Probability": 150
			}
		],
		"masteries": true,
		"masterySections": [
			{
				"Name": "AKM",
				"Templates": [
					"52500592c7109667abb6cbeb"
				]
			}
		],
		"addweaponpreset": true,
		"weaponpresets": [
			{
				"_changeWeaponName": false,
				"_encyclopedia": "52500592c7109667abb6cbeb",
				"_id": "660b4a90010010f388968e18",
				"_items": [
					{
						"_id": "59a45b4ea310853e8020e02c",
						"_tpl": "52500592c7109667abb6cbeb",
						"upd": {
							"StackObjectsCount": 99,
							"Repairable": {
								"MaxDurability": 100,
								"Durability": 100
							},
							"Foldable": {
								"Folded": false
							},
							"FireMode": {
								"FireMode": "single"
							}
						}
					},
					{
						"_id": "2b255c348f41b1d435e83eed",
						"_tpl": "57e3dba62459770f0c32322b",
						"parentId": "59a45b4ea310853e8020e02c",
						"slotId": "mod_pistol_grip"
					},
					{
						"_id": "6e7c37b30d87020344b42dfd",
						"_tpl": "5ac72e895acfc43b321d4bd5",
						"parentId": "59a45b4ea310853e8020e02c",
						"slotId": "mod_muzzle"
					},
					{
						"_id": "00e6897fdf9b2609178f4252",
						"_tpl": "59d6272486f77466146386ff",
						"parentId": "59a45b4ea310853e8020e02c",
						"slotId": "mod_magazine"
					},
					{
						"_id": "6a9a8d44f2a75452b407cb46",
						"_tpl": "57dc347d245977596754e7a1",
						"parentId": "59a45b4ea310853e8020e02c",
						"slotId": "mod_stock"
					},
					{
						"_id": "e4b0200747760435445586dd",
						"_tpl": "57dc334d245977597164366f",
						"parentId": "59a45b4ea310853e8020e02c",
						"slotId": "mod_reciever"
					},
					{
						"_id": "48de431f7092d13944709eca",
						"_tpl": "59d36a0086f7747e673f3946",
						"parentId": "59a45b4ea310853e8020e02c",
						"slotId": "mod_gas_block"
					},
					{
						"_id": "d04e321c6824e6066d99b3ba",
						"_tpl": "57dc32dc245977596d4ef3d3",
						"parentId": "48de431f7092d13944709eca",
						"slotId": "mod_handguard"
					}
				],
				"_name": "Modified Century Arms Draco Stock preset",
				"_parent": "59a45b4ea310853e8020e02c",
				"_type": "Preset"
			}
		]
	}
}